[
  {
    "id": "al-exam-01",
    "title": "AI入门基础",
    "difficulty": "easy",
    "timeLimit": 60,
    "totalScore": 100,
    "passingScore": 60,
    "questionIds": [
      "al-q-002701",
      "al-q-002749",
      "al-q-001551",
      "al-q-001466",
      "al-q-000170",
      "al-q-002299",
      "al-q-000903",
      "al-q-002812",
      "al-q-001300",
      "al-q-000888",
      "al-q-002090",
      "al-q-002927",
      "al-q-003411",
      "al-q-001924",
      "al-q-001292",
      "al-q-003151",
      "al-q-001867",
      "al-q-000296",
      "al-q-002758",
      "al-q-003120",
      "al-q-000382",
      "al-q-000633",
      "al-q-000577",
      "al-q-003137",
      "al-q-000421"
    ],
    "tags": [
      "AI入门"
    ],
    "updatedAt": "2026-07-03T00:00:00.000Z",
    "timeLimitMinutes": 60,
    "summary": "AI入门基础",
    "description": "AI入门基础",
    "slug": "ai入门基础"
  },
  {
    "id": "al-exam-02",
    "title": "学习计划基础",
    "difficulty": "easy",
    "timeLimit": 60,
    "totalScore": 100,
    "passingScore": 60,
    "questionIds": [
      "al-q-001418",
      "al-q-002673",
      "al-q-000773",
      "al-q-002479",
      "al-q-001905",
      "al-q-002055",
      "al-q-001355",
      "al-q-001228",
      "al-q-001840",
      "al-q-003166",
      "al-q-003374",
      "al-q-002956",
      "al-q-001311",
      "al-q-001735",
      "al-q-002289",
      "al-q-001771",
      "al-q-003078",
      "al-q-000322",
      "al-q-001306",
      "al-q-002834",
      "al-q-002210",
      "al-q-001259",
      "al-q-000063",
      "al-q-001073",
      "al-q-001584"
    ],
    "tags": [
      "学习计划"
    ],
    "updatedAt": "2026-07-03T00:00:00.000Z",
    "timeLimitMinutes": 60,
    "summary": "学习计划基础",
    "description": "学习计划基础",
    "slug": "学习计划基础"
  },
  {
    "id": "al-exam-03",
    "title": "知识解释基础",
    "difficulty": "easy",
    "timeLimit": 60,
    "totalScore": 100,
    "passingScore": 60,
    "questionIds": [
      "al-q-002472",
      "al-q-002733",
      "al-q-001698",
      "al-q-002908",
      "al-q-001756",
      "al-q-000562",
      "al-q-001874",
      "al-q-000437",
      "al-q-001482",
      "al-q-003280",
      "al-q-003448",
      "al-q-001809",
      "al-q-002943",
      "al-q-000746",
      "al-q-000312",
      "al-q-000865",
      "al-q-000014",
      "al-q-000731",
      "al-q-000048",
      "al-q-001560",
      "al-q-003098",
      "al-q-000793",
      "al-q-003176",
      "al-q-000787",
      "al-q-003324"
    ],
    "tags": [
      "知识解释"
    ],
    "updatedAt": "2026-07-03T00:00:00.000Z",
    "timeLimitMinutes": 60,
    "summary": "知识解释基础",
    "description": "知识解释基础",
    "slug": "知识解释基础"
  },
  {
    "id": "al-exam-04",
    "title": "题目自测基础",
    "difficulty": "easy",
    "timeLimit": 60,
    "totalScore": 100,
    "passingScore": 60,
    "questionIds": [
      "al-q-002907",
      "al-q-002112",
      "al-q-000689",
      "al-q-003360",
      "al-q-000828",
      "al-q-000281",
      "al-q-000276",
      "al-q-000440",
      "al-q-003484",
      "al-q-002239",
      "al-q-000851",
      "al-q-003006",
      "al-q-002843",
      "al-q-002938",
      "al-q-003295",
      "al-q-002899",
      "al-q-000236",
      "al-q-001596",
      "al-q-000653",
      "al-q-000757",
      "al-q-001960",
      "al-q-001293",
      "al-q-001346",
      "al-q-003188",
      "al-q-001872"
    ],
    "tags": [
      "题目自测"
    ],
    "updatedAt": "2026-07-03T00:00:00.000Z",
    "timeLimitMinutes": 60,
    "summary": "题目自测基础",
    "description": "题目自测基础",
    "slug": "题目自测基础"
  },
  {
    "id": "al-exam-05",
    "title": "笔记总结基础",
    "difficulty": "easy",
    "timeLimit": 60,
    "totalScore": 100,
    "passingScore": 60,
    "questionIds": [
      "al-q-002702",
      "al-q-000071",
      "al-q-001627",
      "al-q-003333",
      "al-q-002354",
      "al-q-001322",
      "al-q-000283",
      "al-q-001045",
      "al-q-000869",
      "al-q-000259",
      "al-q-000547",
      "al-q-001692",
      "al-q-001208",
      "al-q-000367",
      "al-q-000882",
      "al-q-002674",
      "al-q-002319",
      "al-q-003447",
      "al-q-002941",
      "al-q-001248",
      "al-q-001458",
      "al-q-002804",
      "al-q-001835",
      "al-q-002747",
      "al-q-002944"
    ],
    "tags": [
      "笔记总结"
    ],
    "updatedAt": "2026-07-03T00:00:00.000Z",
    "timeLimitMinutes": 60,
    "summary": "笔记总结基础",
    "description": "笔记总结基础",
    "slug": "笔记总结基础"
  },
  {
    "id": "al-exam-06",
    "title": "编程辅助基础",
    "difficulty": "easy",
    "timeLimit": 60,
    "totalScore": 100,
    "passingScore": 60,
    "questionIds": [
      "al-q-002421",
      "al-q-000718",
      "al-q-000400",
      "al-q-003158",
      "al-q-002800",
      "al-q-002857",
      "al-q-002713",
      "al-q-001863",
      "al-q-000436",
      "al-q-001663",
      "al-q-003160",
      "al-q-000240",
      "al-q-000145",
      "al-q-002114",
      "al-q-002128",
      "al-q-003286",
      "al-q-001776",
      "al-q-001145",
      "al-q-000923",
      "al-q-000925",
      "al-q-000523",
      "al-q-000825",
      "al-q-002193",
      "al-q-001792",
      "al-q-003133"
    ],
    "tags": [
      "编程辅助"
    ],
    "updatedAt": "2026-07-03T00:00:00.000Z",
    "timeLimitMinutes": 60,
    "summary": "编程辅助基础",
    "description": "编程辅助基础",
    "slug": "编程辅助基础"
  },
  {
    "id": "al-exam-07",
    "title": "学科场景基础",
    "difficulty": "easy",
    "timeLimit": 60,
    "totalScore": 100,
    "passingScore": 60,
    "questionIds": [
      "al-q-002985",
      "al-q-003381",
      "al-q-001728",
      "al-q-000995",
      "al-q-003271",
      "al-q-003054",
      "al-q-002467",
      "al-q-002038",
      "al-q-001697",
      "al-q-003458",
      "al-q-000109",
      "al-q-003086",
      "al-q-002712",
      "al-q-000904",
      "al-q-002663",
      "al-q-002954",
      "al-q-001954",
      "al-q-000969",
      "al-q-000190",
      "al-q-002715",
      "al-q-001641",
      "al-q-000126",
      "al-q-002377",
      "al-q-001275",
      "al-q-000809"
    ],
    "tags": [
      "学科场景"
    ],
    "updatedAt": "2026-07-03T00:00:00.000Z",
    "timeLimitMinutes": 60,
    "summary": "学科场景基础",
    "description": "学科场景基础",
    "slug": "学科场景基础"
  },
  {
    "id": "al-exam-08",
    "title": "项目辅助基础",
    "difficulty": "easy",
    "timeLimit": 60,
    "totalScore": 100,
    "passingScore": 60,
    "questionIds": [
      "al-q-001133",
      "al-q-002312",
      "al-q-001646",
      "al-q-000948",
      "al-q-000650",
      "al-q-002205",
      "al-q-001165",
      "al-q-002364",
      "al-q-003278",
      "al-q-000467",
      "al-q-000008",
      "al-q-001925",
      "al-q-001026",
      "al-q-000072",
      "al-q-002188",
      "al-q-001274",
      "al-q-002412",
      "al-q-001917",
      "al-q-000581",
      "al-q-000045",
      "al-q-002375",
      "al-q-003014",
      "al-q-000850",
      "al-q-000982",
      "al-q-003408"
    ],
    "tags": [
      "项目辅助"
    ],
    "updatedAt": "2026-07-03T00:00:00.000Z",
    "timeLimitMinutes": 60,
    "summary": "项目辅助基础",
    "description": "项目辅助基础",
    "slug": "项目辅助基础"
  },
  {
    "id": "al-exam-09",
    "title": "事实核查基础",
    "difficulty": "easy",
    "timeLimit": 60,
    "totalScore": 100,
    "passingScore": 60,
    "questionIds": [
      "al-q-000546",
      "al-q-001749",
      "al-q-001194",
      "al-q-001155",
      "al-q-001323",
      "al-q-000716",
      "al-q-000945",
      "al-q-003476",
      "al-q-000597",
      "al-q-000161",
      "al-q-000131",
      "al-q-002481",
      "al-q-000868",
      "al-q-000289",
      "al-q-000540",
      "al-q-002571",
      "al-q-001861",
      "al-q-000272",
      "al-q-001742",
      "al-q-002637",
      "al-q-002570",
      "al-q-002175",
      "al-q-002902",
      "al-q-003385",
      "al-q-001315"
    ],
    "tags": [
      "事实核查"
    ],
    "updatedAt": "2026-07-03T00:00:00.000Z",
    "timeLimitMinutes": 60,
    "summary": "事实核查基础",
    "description": "事实核查基础",
    "slug": "事实核查基础"
  },
  {
    "id": "al-exam-10",
    "title": "工作流模板基础",
    "difficulty": "easy",
    "timeLimit": 60,
    "totalScore": 100,
    "passingScore": 60,
    "questionIds": [
      "al-q-001828",
      "al-q-000023",
      "al-q-000706",
      "al-q-001639",
      "al-q-002083",
      "al-q-001631",
      "al-q-003157",
      "al-q-000066",
      "al-q-002286",
      "al-q-001555",
      "al-q-001731",
      "al-q-001510",
      "al-q-000313",
      "al-q-002077",
      "al-q-002721",
      "al-q-003170",
      "al-q-000971",
      "al-q-003237",
      "al-q-001411",
      "al-q-003250",
      "al-q-000644",
      "al-q-000438",
      "al-q-002627",
      "al-q-000901",
      "al-q-001427"
    ],
    "tags": [
      "工作流模板"
    ],
    "updatedAt": "2026-07-03T00:00:00.000Z",
    "timeLimitMinutes": 60,
    "summary": "工作流模板基础",
    "description": "工作流模板基础",
    "slug": "工作流模板基础"
  },
  {
    "id": "al-exam-11",
    "title": "学习日志基础",
    "difficulty": "easy",
    "timeLimit": 60,
    "totalScore": 100,
    "passingScore": 60,
    "questionIds": [
      "al-q-001377",
      "al-q-002869",
      "al-q-000200",
      "al-q-002287",
      "al-q-003427",
      "al-q-001345",
      "al-q-001681",
      "al-q-000762",
      "al-q-000227",
      "al-q-002147",
      "al-q-001606",
      "al-q-000392",
      "al-q-003371",
      "al-q-001915",
      "al-q-000431",
      "al-q-000288",
      "al-q-000229",
      "al-q-001800",
      "al-q-001415",
      "al-q-002768",
      "al-q-001492",
      "al-q-001719",
      "al-q-002867",
      "al-q-002172",
      "al-q-002886"
    ],
    "tags": [
      "学习日志"
    ],
    "updatedAt": "2026-07-03T00:00:00.000Z",
    "timeLimitMinutes": 60,
    "summary": "学习日志基础",
    "description": "学习日志基础",
    "slug": "学习日志基础"
  },
  {
    "id": "al-exam-12",
    "title": "输出评估基础",
    "difficulty": "easy",
    "timeLimit": 60,
    "totalScore": 100,
    "passingScore": 60,
    "questionIds": [
      "al-q-001144",
      "al-q-000450",
      "al-q-000037",
      "al-q-000772",
      "al-q-001433",
      "al-q-002091",
      "al-q-000918",
      "al-q-000387",
      "al-q-003404",
      "al-q-000306",
      "al-q-000362",
      "al-q-001930",
      "al-q-001277",
      "al-q-000771",
      "al-q-000070",
      "al-q-003463",
      "al-q-001454",
      "al-q-002808",
      "al-q-003380",
      "al-q-002490",
      "al-q-002226",
      "al-q-001008",
      "al-q-002315",
      "al-q-000188",
      "al-q-001539"
    ],
    "tags": [
      "输出评估"
    ],
    "updatedAt": "2026-07-03T00:00:00.000Z",
    "timeLimitMinutes": 60,
    "summary": "输出评估基础",
    "description": "输出评估基础",
    "slug": "输出评估基础"
  },
  {
    "id": "al-exam-13",
    "title": "安全规范基础",
    "difficulty": "easy",
    "timeLimit": 60,
    "totalScore": 100,
    "passingScore": 60,
    "questionIds": [
      "al-q-003297",
      "al-q-001265",
      "al-q-000396",
      "al-q-001941",
      "al-q-002981",
      "al-q-001543",
      "al-q-000473",
      "al-q-000141",
      "al-q-002011",
      "al-q-003459",
      "al-q-000976",
      "al-q-002483",
      "al-q-003350",
      "al-q-001923",
      "al-q-002942",
      "al-q-000590",
      "al-q-001221",
      "al-q-001067",
      "al-q-001153",
      "al-q-000815",
      "al-q-000862",
      "al-q-000040",
      "al-q-001987",
      "al-q-002628",
      "al-q-001621"
    ],
    "tags": [
      "安全规范"
    ],
    "updatedAt": "2026-07-03T00:00:00.000Z",
    "timeLimitMinutes": 60,
    "summary": "安全规范基础",
    "description": "安全规范基础",
    "slug": "安全规范基础"
  },
  {
    "id": "al-exam-14",
    "title": "AI综合基础",
    "difficulty": "easy",
    "timeLimit": 60,
    "totalScore": 100,
    "passingScore": 60,
    "questionIds": [
      "al-q-002039",
      "al-q-002222",
      "al-q-001437",
      "al-q-001940",
      "al-q-002191",
      "al-q-002420",
      "al-q-002612",
      "al-q-000369",
      "al-q-002248",
      "al-q-000538",
      "al-q-000244",
      "al-q-001049",
      "al-q-001468",
      "al-q-002058",
      "al-q-000587",
      "al-q-003110",
      "al-q-002563",
      "al-q-002183",
      "al-q-002839",
      "al-q-000912",
      "al-q-001018",
      "al-q-002684",
      "al-q-000338",
      "al-q-000348",
      "al-q-000975"
    ],
    "tags": [
      "AI综合"
    ],
    "updatedAt": "2026-07-03T00:00:00.000Z",
    "timeLimitMinutes": 60,
    "summary": "AI综合基础",
    "description": "AI综合基础",
    "slug": "ai综合基础"
  },
  {
    "id": "al-exam-15",
    "title": "AI入门基础",
    "difficulty": "easy",
    "timeLimit": 60,
    "totalScore": 100,
    "passingScore": 60,
    "questionIds": [
      "al-q-000295",
      "al-q-000951",
      "al-q-001253",
      "al-q-002525",
      "al-q-001844",
      "al-q-002882",
      "al-q-002877",
      "al-q-000421",
      "al-q-000172",
      "al-q-000472",
      "al-q-000382",
      "al-q-000429",
      "al-q-001420",
      "al-q-002252",
      "al-q-002531",
      "al-q-000026",
      "al-q-000681",
      "al-q-003038",
      "al-q-000316",
      "al-q-001413",
      "al-q-001106",
      "al-q-002308",
      "al-q-001705",
      "al-q-000170",
      "al-q-001185"
    ],
    "tags": [
      "AI入门"
    ],
    "updatedAt": "2026-07-03T00:00:00.000Z",
    "timeLimitMinutes": 60,
    "summary": "AI入门基础",
    "description": "AI入门基础",
    "slug": "ai入门基础"
  },
  {
    "id": "al-exam-16",
    "title": "学习计划基础",
    "difficulty": "easy",
    "timeLimit": 60,
    "totalScore": 100,
    "passingScore": 60,
    "questionIds": [
      "al-q-002645",
      "al-q-003090",
      "al-q-002640",
      "al-q-002376",
      "al-q-002991",
      "al-q-002328",
      "al-q-000827",
      "al-q-002150",
      "al-q-002068",
      "al-q-002972",
      "al-q-002173",
      "al-q-003136",
      "al-q-003093",
      "al-q-001544",
      "al-q-001682",
      "al-q-002549",
      "al-q-002772",
      "al-q-001630",
      "al-q-002344",
      "al-q-001005",
      "al-q-001594",
      "al-q-002361",
      "al-q-002871",
      "al-q-001442",
      "al-q-003446"
    ],
    "tags": [
      "学习计划"
    ],
    "updatedAt": "2026-07-03T00:00:00.000Z",
    "timeLimitMinutes": 60,
    "summary": "学习计划基础",
    "description": "学习计划基础",
    "slug": "学习计划基础"
  },
  {
    "id": "al-exam-17",
    "title": "知识解释基础",
    "difficulty": "easy",
    "timeLimit": 60,
    "totalScore": 100,
    "passingScore": 60,
    "questionIds": [
      "al-q-000812",
      "al-q-001756",
      "al-q-003392",
      "al-q-000977",
      "al-q-003448",
      "al-q-002744",
      "al-q-002518",
      "al-q-002982",
      "al-q-002167",
      "al-q-003419",
      "al-q-002282",
      "al-q-001896",
      "al-q-001344",
      "al-q-000928",
      "al-q-002235",
      "al-q-000656",
      "al-q-000694",
      "al-q-002464",
      "al-q-001112",
      "al-q-001057",
      "al-q-000257",
      "al-q-000056",
      "al-q-000237",
      "al-q-001230",
      "al-q-000880"
    ],
    "tags": [
      "知识解释"
    ],
    "updatedAt": "2026-07-03T00:00:00.000Z",
    "timeLimitMinutes": 60,
    "summary": "知识解释基础",
    "description": "知识解释基础",
    "slug": "知识解释基础"
  },
  {
    "id": "al-exam-18",
    "title": "题目自测基础",
    "difficulty": "easy",
    "timeLimit": 60,
    "totalScore": 100,
    "passingScore": 60,
    "questionIds": [
      "al-q-003006",
      "al-q-002699",
      "al-q-003454",
      "al-q-000849",
      "al-q-001334",
      "al-q-003360",
      "al-q-002843",
      "al-q-001081",
      "al-q-000851",
      "al-q-001336",
      "al-q-000877",
      "al-q-001772",
      "al-q-001219",
      "al-q-000168",
      "al-q-002484",
      "al-q-001876",
      "al-q-001125",
      "al-q-001024",
      "al-q-000411",
      "al-q-003438",
      "al-q-000866",
      "al-q-003295",
      "al-q-003429",
      "al-q-003493",
      "al-q-000727"
    ],
    "tags": [
      "题目自测"
    ],
    "updatedAt": "2026-07-03T00:00:00.000Z",
    "timeLimitMinutes": 60,
    "summary": "题目自测基础",
    "description": "题目自测基础",
    "slug": "题目自测基础"
  },
  {
    "id": "al-exam-19",
    "title": "笔记总结基础",
    "difficulty": "easy",
    "timeLimit": 60,
    "totalScore": 100,
    "passingScore": 60,
    "questionIds": [
      "al-q-002939",
      "al-q-002804",
      "al-q-000547",
      "al-q-001289",
      "al-q-000447",
      "al-q-001704",
      "al-q-000461",
      "al-q-001132",
      "al-q-001458",
      "al-q-003279",
      "al-q-002700",
      "al-q-001949",
      "al-q-000635",
      "al-q-000595",
      "al-q-000068",
      "al-q-001248",
      "al-q-002327",
      "al-q-003141",
      "al-q-001116",
      "al-q-001926",
      "al-q-002941",
      "al-q-001903",
      "al-q-002716",
      "al-q-003479",
      "al-q-002931"
    ],
    "tags": [
      "笔记总结"
    ],
    "updatedAt": "2026-07-03T00:00:00.000Z",
    "timeLimitMinutes": 60,
    "summary": "笔记总结基础",
    "description": "笔记总结基础",
    "slug": "笔记总结基础"
  },
  {
    "id": "al-exam-20",
    "title": "编程辅助基础",
    "difficulty": "easy",
    "timeLimit": 60,
    "totalScore": 100,
    "passingScore": 60,
    "questionIds": [
      "al-q-003259",
      "al-q-000664",
      "al-q-000464",
      "al-q-000745",
      "al-q-002433",
      "al-q-000858",
      "al-q-003431",
      "al-q-001247",
      "al-q-002994",
      "al-q-000822",
      "al-q-000344",
      "al-q-003171",
      "al-q-001792",
      "al-q-003249",
      "al-q-003456",
      "al-q-000916",
      "al-q-001216",
      "al-q-000778",
      "al-q-000623",
      "al-q-002128",
      "al-q-003106",
      "al-q-001947",
      "al-q-002102",
      "al-q-003443",
      "al-q-002148"
    ],
    "tags": [
      "编程辅助"
    ],
    "updatedAt": "2026-07-03T00:00:00.000Z",
    "timeLimitMinutes": 60,
    "summary": "编程辅助基础",
    "description": "编程辅助基础",
    "slug": "编程辅助基础"
  },
  {
    "id": "al-exam-21",
    "title": "学科场景基础",
    "difficulty": "easy",
    "timeLimit": 60,
    "totalScore": 100,
    "passingScore": 60,
    "questionIds": [
      "al-q-000584",
      "al-q-001231",
      "al-q-001197",
      "al-q-001617",
      "al-q-002813",
      "al-q-002142",
      "al-q-000109",
      "al-q-001794",
      "al-q-000707",
      "al-q-000480",
      "al-q-000905",
      "al-q-002253",
      "al-q-000218",
      "al-q-000897",
      "al-q-002707",
      "al-q-003420",
      "al-q-000626",
      "al-q-000836",
      "al-q-001757",
      "al-q-000064",
      "al-q-000082",
      "al-q-000805",
      "al-q-003480",
      "al-q-001487",
      "al-q-001556"
    ],
    "tags": [
      "学科场景"
    ],
    "updatedAt": "2026-07-03T00:00:00.000Z",
    "timeLimitMinutes": 60,
    "summary": "学科场景基础",
    "description": "学科场景基础",
    "slug": "学科场景基础"
  },
  {
    "id": "al-exam-22",
    "title": "项目辅助基础",
    "difficulty": "easy",
    "timeLimit": 60,
    "totalScore": 100,
    "passingScore": 60,
    "questionIds": [
      "al-q-001143",
      "al-q-002016",
      "al-q-001917",
      "al-q-000008",
      "al-q-000282",
      "al-q-001629",
      "al-q-001842",
      "al-q-000661",
      "al-q-000873",
      "al-q-003094",
      "al-q-001075",
      "al-q-000265",
      "al-q-002414",
      "al-q-002471",
      "al-q-000352",
      "al-q-002425",
      "al-q-003234",
      "al-q-002901",
      "al-q-001490",
      "al-q-000122",
      "al-q-003409",
      "al-q-002675",
      "al-q-000691",
      "al-q-002307",
      "al-q-001167"
    ],
    "tags": [
      "项目辅助"
    ],
    "updatedAt": "2026-07-03T00:00:00.000Z",
    "timeLimitMinutes": 60,
    "summary": "项目辅助基础",
    "description": "项目辅助基础",
    "slug": "项目辅助基础"
  },
  {
    "id": "al-exam-23",
    "title": "事实核查基础",
    "difficulty": "easy",
    "timeLimit": 60,
    "totalScore": 100,
    "passingScore": 60,
    "questionIds": [
      "al-q-002463",
      "al-q-000597",
      "al-q-002080",
      "al-q-000395",
      "al-q-000324",
      "al-q-001182",
      "al-q-002971",
      "al-q-000521",
      "al-q-002847",
      "al-q-002175",
      "al-q-001432",
      "al-q-000514",
      "al-q-002436",
      "al-q-002429",
      "al-q-002821",
      "al-q-001628",
      "al-q-001514",
      "al-q-001476",
      "al-q-001323",
      "al-q-001194",
      "al-q-002810",
      "al-q-002968",
      "al-q-001527",
      "al-q-000548",
      "al-q-002162"
    ],
    "tags": [
      "事实核查"
    ],
    "updatedAt": "2026-07-03T00:00:00.000Z",
    "timeLimitMinutes": 60,
    "summary": "事实核查基础",
    "description": "事实核查基础",
    "slug": "事实核查基础"
  },
  {
    "id": "al-exam-24",
    "title": "工作流模板基础",
    "difficulty": "easy",
    "timeLimit": 60,
    "totalScore": 100,
    "passingScore": 60,
    "questionIds": [
      "al-q-000023",
      "al-q-003108",
      "al-q-001141",
      "al-q-002776",
      "al-q-001767",
      "al-q-002872",
      "al-q-000688",
      "al-q-002921",
      "al-q-002779",
      "al-q-001538",
      "al-q-002918",
      "al-q-003172",
      "al-q-001093",
      "al-q-001907",
      "al-q-001429",
      "al-q-001080",
      "al-q-003442",
      "al-q-000699",
      "al-q-003112",
      "al-q-002133",
      "al-q-001115",
      "al-q-002050",
      "al-q-002343",
      "al-q-001851",
      "al-q-003306"
    ],
    "tags": [
      "工作流模板"
    ],
    "updatedAt": "2026-07-03T00:00:00.000Z",
    "timeLimitMinutes": 60,
    "summary": "工作流模板基础",
    "description": "工作流模板基础",
    "slug": "工作流模板基础"
  },
  {
    "id": "al-exam-25",
    "title": "学习日志基础",
    "difficulty": "easy",
    "timeLimit": 60,
    "totalScore": 100,
    "passingScore": 60,
    "questionIds": [
      "al-q-001678",
      "al-q-002905",
      "al-q-002309",
      "al-q-002947",
      "al-q-000298",
      "al-q-000762",
      "al-q-001180",
      "al-q-001486",
      "al-q-003359",
      "al-q-000098",
      "al-q-001656",
      "al-q-001009",
      "al-q-001773",
      "al-q-001291",
      "al-q-000952",
      "al-q-003497",
      "al-q-003211",
      "al-q-000659",
      "al-q-002886",
      "al-q-002250",
      "al-q-000708",
      "al-q-001529",
      "al-q-001110",
      "al-q-002287",
      "al-q-000890"
    ],
    "tags": [
      "学习日志"
    ],
    "updatedAt": "2026-07-03T00:00:00.000Z",
    "timeLimitMinutes": 60,
    "summary": "学习日志基础",
    "description": "学习日志基础",
    "slug": "学习日志基础"
  },
  {
    "id": "al-exam-26",
    "title": "输出评估基础",
    "difficulty": "easy",
    "timeLimit": 60,
    "totalScore": 100,
    "passingScore": 60,
    "questionIds": [
      "al-q-001982",
      "al-q-001201",
      "al-q-000211",
      "al-q-002849",
      "al-q-002851",
      "al-q-001280",
      "al-q-000088",
      "al-q-002022",
      "al-q-001144",
      "al-q-000340",
      "al-q-002669",
      "al-q-000524",
      "al-q-001548",
      "al-q-002596",
      "al-q-001702",
      "al-q-000883",
      "al-q-002001",
      "al-q-002808",
      "al-q-000195",
      "al-q-002181",
      "al-q-001597",
      "al-q-002091",
      "al-q-000915",
      "al-q-002862",
      "al-q-000823"
    ],
    "tags": [
      "输出评估"
    ],
    "updatedAt": "2026-07-03T00:00:00.000Z",
    "timeLimitMinutes": 60,
    "summary": "输出评估基础",
    "description": "输出评估基础",
    "slug": "输出评估基础"
  },
  {
    "id": "al-exam-27",
    "title": "安全规范基础",
    "difficulty": "easy",
    "timeLimit": 60,
    "totalScore": 100,
    "passingScore": 60,
    "questionIds": [
      "al-q-001801",
      "al-q-003369",
      "al-q-001540",
      "al-q-003088",
      "al-q-002880",
      "al-q-001621",
      "al-q-000213",
      "al-q-002638",
      "al-q-002792",
      "al-q-002633",
      "al-q-001364",
      "al-q-001833",
      "al-q-000061",
      "al-q-001971",
      "al-q-001181",
      "al-q-001666",
      "al-q-001298",
      "al-q-002115",
      "al-q-002981",
      "al-q-003096",
      "al-q-001987",
      "al-q-000857",
      "al-q-002434",
      "al-q-000248",
      "al-q-002628"
    ],
    "tags": [
      "安全规范"
    ],
    "updatedAt": "2026-07-03T00:00:00.000Z",
    "timeLimitMinutes": 60,
    "summary": "安全规范基础",
    "description": "安全规范基础",
    "slug": "安全规范基础"
  },
  {
    "id": "al-exam-28",
    "title": "AI综合基础",
    "difficulty": "easy",
    "timeLimit": 60,
    "totalScore": 100,
    "passingScore": 60,
    "questionIds": [
      "al-q-002891",
      "al-q-001964",
      "al-q-002363",
      "al-q-000710",
      "al-q-000169",
      "al-q-000821",
      "al-q-000579",
      "al-q-000641",
      "al-q-001437",
      "al-q-002497",
      "al-q-002775",
      "al-q-002248",
      "al-q-001284",
      "al-q-002999",
      "al-q-001970",
      "al-q-000912",
      "al-q-002694",
      "al-q-002576",
      "al-q-000791",
      "al-q-001147",
      "al-q-001338",
      "al-q-000677",
      "al-q-001312",
      "al-q-000147",
      "al-q-000583"
    ],
    "tags": [
      "AI综合"
    ],
    "updatedAt": "2026-07-03T00:00:00.000Z",
    "timeLimitMinutes": 60,
    "summary": "AI综合基础",
    "description": "AI综合基础",
    "slug": "ai综合基础"
  },
  {
    "id": "al-exam-29",
    "title": "AI入门基础",
    "difficulty": "easy",
    "timeLimit": 60,
    "totalScore": 100,
    "passingScore": 60,
    "questionIds": [
      "al-q-000472",
      "al-q-000782",
      "al-q-001290",
      "al-q-000444",
      "al-q-001006",
      "al-q-000164",
      "al-q-001257",
      "al-q-001300",
      "al-q-002526",
      "al-q-002649",
      "al-q-001053",
      "al-q-001699",
      "al-q-000667",
      "al-q-002179",
      "al-q-002244",
      "al-q-002803",
      "al-q-001705",
      "al-q-000888",
      "al-q-002898",
      "al-q-003402",
      "al-q-003411",
      "al-q-001679",
      "al-q-000775",
      "al-q-001021",
      "al-q-002135"
    ],
    "tags": [
      "AI入门"
    ],
    "updatedAt": "2026-07-03T00:00:00.000Z",
    "timeLimitMinutes": 60,
    "summary": "AI入门基础",
    "description": "AI入门基础",
    "slug": "ai入门基础"
  },
  {
    "id": "al-exam-30",
    "title": "学习计划基础",
    "difficulty": "easy",
    "timeLimit": 60,
    "totalScore": 100,
    "passingScore": 60,
    "questionIds": [
      "al-q-002057",
      "al-q-001961",
      "al-q-000094",
      "al-q-000932",
      "al-q-000773",
      "al-q-000874",
      "al-q-002834",
      "al-q-003139",
      "al-q-003317",
      "al-q-002303",
      "al-q-003374",
      "al-q-002915",
      "al-q-000217",
      "al-q-001827",
      "al-q-000680",
      "al-q-003323",
      "al-q-000898",
      "al-q-001928",
      "al-q-001613",
      "al-q-001771",
      "al-q-003294",
      "al-q-002584",
      "al-q-000598",
      "al-q-001393",
      "al-q-001886"
    ],
    "tags": [
      "学习计划"
    ],
    "updatedAt": "2026-07-03T00:00:00.000Z",
    "timeLimitMinutes": 60,
    "summary": "学习计划基础",
    "description": "学习计划基础",
    "slug": "学习计划基础"
  },
  {
    "id": "al-exam-31",
    "title": "知识解释基础",
    "difficulty": "easy",
    "timeLimit": 60,
    "totalScore": 100,
    "passingScore": 60,
    "questionIds": [
      "al-q-000812",
      "al-q-001114",
      "al-q-000797",
      "al-q-001212",
      "al-q-001505",
      "al-q-002393",
      "al-q-002178",
      "al-q-001999",
      "al-q-002943",
      "al-q-003032",
      "al-q-000928",
      "al-q-002304",
      "al-q-002401",
      "al-q-000471",
      "al-q-000370",
      "al-q-002846",
      "al-q-003210",
      "al-q-000731",
      "al-q-000078",
      "al-q-002093",
      "al-q-001734",
      "al-q-001739",
      "al-q-003067",
      "al-q-000475",
      "al-q-000717"
    ],
    "tags": [
      "知识解释"
    ],
    "updatedAt": "2026-07-03T00:00:00.000Z",
    "timeLimitMinutes": 60,
    "summary": "知识解释基础",
    "description": "知识解释基础",
    "slug": "知识解释基础"
  },
  {
    "id": "al-exam-32",
    "title": "题目自测基础",
    "difficulty": "easy",
    "timeLimit": 60,
    "totalScore": 100,
    "passingScore": 60,
    "questionIds": [
      "al-q-001047",
      "al-q-001081",
      "al-q-000851",
      "al-q-000879",
      "al-q-003454",
      "al-q-001762",
      "al-q-001994",
      "al-q-000909",
      "al-q-001848",
      "al-q-001862",
      "al-q-000984",
      "al-q-001217",
      "al-q-000630",
      "al-q-000225",
      "al-q-001170",
      "al-q-000469",
      "al-q-003066",
      "al-q-001285",
      "al-q-002300",
      "al-q-003258",
      "al-q-003233",
      "al-q-002105",
      "al-q-000927",
      "al-q-001900",
      "al-q-001156"
    ],
    "tags": [
      "题目自测"
    ],
    "updatedAt": "2026-07-03T00:00:00.000Z",
    "timeLimitMinutes": 60,
    "summary": "题目自测基础",
    "description": "题目自测基础",
    "slug": "题目自测基础"
  },
  {
    "id": "al-exam-33",
    "title": "笔记总结基础",
    "difficulty": "easy",
    "timeLimit": 60,
    "totalScore": 100,
    "passingScore": 60,
    "questionIds": [
      "al-q-002939",
      "al-q-002740",
      "al-q-000882",
      "al-q-000445",
      "al-q-003354",
      "al-q-000367",
      "al-q-001488",
      "al-q-001017",
      "al-q-000449",
      "al-q-002804",
      "al-q-003433",
      "al-q-002319",
      "al-q-000961",
      "al-q-002747",
      "al-q-002958",
      "al-q-001441",
      "al-q-003231",
      "al-q-002021",
      "al-q-001116",
      "al-q-000600",
      "al-q-003255",
      "al-q-000705",
      "al-q-001326",
      "al-q-002830",
      "al-q-002960"
    ],
    "tags": [
      "笔记总结"
    ],
    "updatedAt": "2026-07-03T00:00:00.000Z",
    "timeLimitMinutes": 60,
    "summary": "笔记总结基础",
    "description": "笔记总结基础",
    "slug": "笔记总结基础"
  },
  {
    "id": "al-exam-34",
    "title": "编程辅助基础",
    "difficulty": "easy",
    "timeLimit": 60,
    "totalScore": 100,
    "passingScore": 60,
    "questionIds": [
      "al-q-001205",
      "al-q-002024",
      "al-q-003431",
      "al-q-001378",
      "al-q-000622",
      "al-q-001453",
      "al-q-001162",
      "al-q-002417",
      "al-q-003343",
      "al-q-001316",
      "al-q-002368",
      "al-q-002284",
      "al-q-001585",
      "al-q-000456",
      "al-q-000240",
      "al-q-001216",
      "al-q-000317",
      "al-q-001096",
      "al-q-003050",
      "al-q-002053",
      "al-q-000855",
      "al-q-000645",
      "al-q-002421",
      "al-q-001892",
      "al-q-001599"
    ],
    "tags": [
      "编程辅助"
    ],
    "updatedAt": "2026-07-03T00:00:00.000Z",
    "timeLimitMinutes": 60,
    "summary": "编程辅助基础",
    "description": "编程辅助基础",
    "slug": "编程辅助基础"
  },
  {
    "id": "al-exam-35",
    "title": "学科场景基础",
    "difficulty": "easy",
    "timeLimit": 60,
    "totalScore": 100,
    "passingScore": 60,
    "questionIds": [
      "al-q-003298",
      "al-q-000805",
      "al-q-002292",
      "al-q-002550",
      "al-q-001351",
      "al-q-000218",
      "al-q-000427",
      "al-q-003212",
      "al-q-002137",
      "al-q-001419",
      "al-q-001273",
      "al-q-003214",
      "al-q-003054",
      "al-q-003346",
      "al-q-003005",
      "al-q-002985",
      "al-q-003388",
      "al-q-002197",
      "al-q-001226",
      "al-q-000186",
      "al-q-001401",
      "al-q-001728",
      "al-q-000564",
      "al-q-001826",
      "al-q-002707"
    ],
    "tags": [
      "学科场景"
    ],
    "updatedAt": "2026-07-03T00:00:00.000Z",
    "timeLimitMinutes": 60,
    "summary": "学科场景基础",
    "description": "学科场景基础",
    "slug": "学科场景基础"
  },
  {
    "id": "al-exam-36",
    "title": "项目辅助进阶",
    "difficulty": "medium",
    "timeLimit": 60,
    "totalScore": 100,
    "passingScore": 60,
    "questionIds": [
      "al-q-000747",
      "al-q-001472",
      "al-q-000265",
      "al-q-001223",
      "al-q-001165",
      "al-q-000672",
      "al-q-001304",
      "al-q-002218",
      "al-q-002154",
      "al-q-003361",
      "al-q-002200",
      "al-q-002919",
      "al-q-002394",
      "al-q-000282",
      "al-q-003073",
      "al-q-001097",
      "al-q-003014",
      "al-q-001072",
      "al-q-000532",
      "al-q-000982",
      "al-q-003124",
      "al-q-001499",
      "al-q-001553",
      "al-q-000423",
      "al-q-000581"
    ],
    "tags": [
      "项目辅助"
    ],
    "updatedAt": "2026-07-03T00:00:00.000Z",
    "timeLimitMinutes": 60,
    "summary": "项目辅助进阶",
    "description": "项目辅助进阶",
    "slug": "项目辅助进阶"
  },
  {
    "id": "al-exam-37",
    "title": "事实核查进阶",
    "difficulty": "medium",
    "timeLimit": 60,
    "totalScore": 100,
    "passingScore": 60,
    "questionIds": [
      "al-q-000566",
      "al-q-000853",
      "al-q-002052",
      "al-q-002080",
      "al-q-002003",
      "al-q-002463",
      "al-q-002858",
      "al-q-003331",
      "al-q-002190",
      "al-q-002683",
      "al-q-002489",
      "al-q-002443",
      "al-q-000069",
      "al-q-001514",
      "al-q-001396",
      "al-q-002264",
      "al-q-000863",
      "al-q-002752",
      "al-q-000079",
      "al-q-000025",
      "al-q-003037",
      "al-q-001215",
      "al-q-000289",
      "al-q-003284",
      "al-q-001733"
    ],
    "tags": [
      "事实核查"
    ],
    "updatedAt": "2026-07-03T00:00:00.000Z",
    "timeLimitMinutes": 60,
    "summary": "事实核查进阶",
    "description": "事实核查进阶",
    "slug": "事实核查进阶"
  },
  {
    "id": "al-exam-38",
    "title": "工作流模板进阶",
    "difficulty": "medium",
    "timeLimit": 60,
    "totalScore": 100,
    "passingScore": 60,
    "questionIds": [
      "al-q-002296",
      "al-q-000682",
      "al-q-000958",
      "al-q-001921",
      "al-q-003262",
      "al-q-003175",
      "al-q-002893",
      "al-q-001379",
      "al-q-003173",
      "al-q-002378",
      "al-q-000922",
      "al-q-001727",
      "al-q-001115",
      "al-q-000106",
      "al-q-001980",
      "al-q-002446",
      "al-q-000902",
      "al-q-001177",
      "al-q-003157",
      "al-q-002389",
      "al-q-002779",
      "al-q-003154",
      "al-q-001235",
      "al-q-002373",
      "al-q-000799"
    ],
    "tags": [
      "工作流模板"
    ],
    "updatedAt": "2026-07-03T00:00:00.000Z",
    "timeLimitMinutes": 60,
    "summary": "工作流模板进阶",
    "description": "工作流模板进阶",
    "slug": "工作流模板进阶"
  },
  {
    "id": "al-exam-39",
    "title": "学习日志进阶",
    "difficulty": "medium",
    "timeLimit": 60,
    "totalScore": 100,
    "passingScore": 60,
    "questionIds": [
      "al-q-002887",
      "al-q-000307",
      "al-q-003057",
      "al-q-002905",
      "al-q-000748",
      "al-q-001180",
      "al-q-002250",
      "al-q-002017",
      "al-q-000542",
      "al-q-001288",
      "al-q-000762",
      "al-q-001009",
      "al-q-000534",
      "al-q-000431",
      "al-q-002665",
      "al-q-002004",
      "al-q-002969",
      "al-q-003359",
      "al-q-001022",
      "al-q-002617",
      "al-q-003477",
      "al-q-000201",
      "al-q-000247",
      "al-q-002951",
      "al-q-002879"
    ],
    "tags": [
      "学习日志"
    ],
    "updatedAt": "2026-07-03T00:00:00.000Z",
    "timeLimitMinutes": 60,
    "summary": "学习日志进阶",
    "description": "学习日志进阶",
    "slug": "学习日志进阶"
  },
  {
    "id": "al-exam-40",
    "title": "输出评估进阶",
    "difficulty": "medium",
    "timeLimit": 60,
    "totalScore": 100,
    "passingScore": 60,
    "questionIds": [
      "al-q-002168",
      "al-q-002315",
      "al-q-002862",
      "al-q-003190",
      "al-q-000823",
      "al-q-001548",
      "al-q-002724",
      "al-q-001433",
      "al-q-001381",
      "al-q-001763",
      "al-q-000067",
      "al-q-000605",
      "al-q-002992",
      "al-q-000741",
      "al-q-003488",
      "al-q-000095",
      "al-q-000361",
      "al-q-002506",
      "al-q-002490",
      "al-q-001652",
      "al-q-000487",
      "al-q-000211",
      "al-q-001702",
      "al-q-002044",
      "al-q-001309"
    ],
    "tags": [
      "输出评估"
    ],
    "updatedAt": "2026-07-03T00:00:00.000Z",
    "timeLimitMinutes": 60,
    "summary": "输出评估进阶",
    "description": "输出评估进阶",
    "slug": "输出评估进阶"
  },
  {
    "id": "al-exam-41",
    "title": "安全规范进阶",
    "difficulty": "medium",
    "timeLimit": 60,
    "totalScore": 100,
    "passingScore": 60,
    "questionIds": [
      "al-q-002685",
      "al-q-001941",
      "al-q-001181",
      "al-q-000092",
      "al-q-002754",
      "al-q-002011",
      "al-q-001821",
      "al-q-000937",
      "al-q-003198",
      "al-q-001364",
      "al-q-000517",
      "al-q-003363",
      "al-q-000511",
      "al-q-001031",
      "al-q-003466",
      "al-q-002545",
      "al-q-000213",
      "al-q-002738",
      "al-q-003107",
      "al-q-002032",
      "al-q-003350",
      "al-q-001464",
      "al-q-002187",
      "al-q-002070",
      "al-q-000968"
    ],
    "tags": [
      "安全规范"
    ],
    "updatedAt": "2026-07-03T00:00:00.000Z",
    "timeLimitMinutes": 60,
    "summary": "安全规范进阶",
    "description": "安全规范进阶",
    "slug": "安全规范进阶"
  },
  {
    "id": "al-exam-42",
    "title": "AI综合进阶",
    "difficulty": "medium",
    "timeLimit": 60,
    "totalScore": 100,
    "passingScore": 60,
    "questionIds": [
      "al-q-000077",
      "al-q-000791",
      "al-q-000944",
      "al-q-002642",
      "al-q-001312",
      "al-q-002694",
      "al-q-002937",
      "al-q-002183",
      "al-q-001191",
      "al-q-000724",
      "al-q-003125",
      "al-q-000845",
      "al-q-000588",
      "al-q-001268",
      "al-q-000810",
      "al-q-002420",
      "al-q-002970",
      "al-q-000369",
      "al-q-000835",
      "al-q-001638",
      "al-q-002232",
      "al-q-001089",
      "al-q-001916",
      "al-q-003299",
      "al-q-001873"
    ],
    "tags": [
      "AI综合"
    ],
    "updatedAt": "2026-07-03T00:00:00.000Z",
    "timeLimitMinutes": 60,
    "summary": "AI综合进阶",
    "description": "AI综合进阶",
    "slug": "ai综合进阶"
  },
  {
    "id": "al-exam-43",
    "title": "AI入门进阶",
    "difficulty": "medium",
    "timeLimit": 60,
    "totalScore": 100,
    "passingScore": 60,
    "questionIds": [
      "al-q-001318",
      "al-q-000667",
      "al-q-003342",
      "al-q-000552",
      "al-q-000424",
      "al-q-002273",
      "al-q-003491",
      "al-q-002383",
      "al-q-002224",
      "al-q-002535",
      "al-q-001705",
      "al-q-003422",
      "al-q-002213",
      "al-q-000834",
      "al-q-002812",
      "al-q-002081",
      "al-q-000215",
      "al-q-000633",
      "al-q-000533",
      "al-q-001185",
      "al-q-001450",
      "al-q-002244",
      "al-q-002012",
      "al-q-001852",
      "al-q-000042"
    ],
    "tags": [
      "AI入门"
    ],
    "updatedAt": "2026-07-03T00:00:00.000Z",
    "timeLimitMinutes": 60,
    "summary": "AI入门进阶",
    "description": "AI入门进阶",
    "slug": "ai入门进阶"
  },
  {
    "id": "al-exam-44",
    "title": "学习计划进阶",
    "difficulty": "medium",
    "timeLimit": 60,
    "totalScore": 100,
    "passingScore": 60,
    "questionIds": [
      "al-q-002173",
      "al-q-002582",
      "al-q-002791",
      "al-q-000094",
      "al-q-002150",
      "al-q-003367",
      "al-q-003329",
      "al-q-001393",
      "al-q-001355",
      "al-q-002455",
      "al-q-000932",
      "al-q-001602",
      "al-q-003446",
      "al-q-001592",
      "al-q-001507",
      "al-q-003043",
      "al-q-001836",
      "al-q-000685",
      "al-q-003308",
      "al-q-002459",
      "al-q-000611",
      "al-q-002328",
      "al-q-002210",
      "al-q-003238",
      "al-q-001347"
    ],
    "tags": [
      "学习计划"
    ],
    "updatedAt": "2026-07-03T00:00:00.000Z",
    "timeLimitMinutes": 60,
    "summary": "学习计划进阶",
    "description": "学习计划进阶",
    "slug": "学习计划进阶"
  },
  {
    "id": "al-exam-45",
    "title": "知识解释进阶",
    "difficulty": "medium",
    "timeLimit": 60,
    "totalScore": 100,
    "passingScore": 60,
    "questionIds": [
      "al-q-000162",
      "al-q-001272",
      "al-q-002371",
      "al-q-002677",
      "al-q-003034",
      "al-q-000880",
      "al-q-000793",
      "al-q-001999",
      "al-q-002304",
      "al-q-001758",
      "al-q-000156",
      "al-q-001934",
      "al-q-000787",
      "al-q-002034",
      "al-q-002230",
      "al-q-002409",
      "al-q-002178",
      "al-q-000936",
      "al-q-000354",
      "al-q-003184",
      "al-q-002982",
      "al-q-003111",
      "al-q-000207",
      "al-q-000078",
      "al-q-002464"
    ],
    "tags": [
      "知识解释"
    ],
    "updatedAt": "2026-07-03T00:00:00.000Z",
    "timeLimitMinutes": 60,
    "summary": "知识解释进阶",
    "description": "知识解释进阶",
    "slug": "知识解释进阶"
  },
  {
    "id": "al-exam-46",
    "title": "题目自测进阶",
    "difficulty": "medium",
    "timeLimit": 60,
    "totalScore": 100,
    "passingScore": 60,
    "questionIds": [
      "al-q-003030",
      "al-q-000238",
      "al-q-001118",
      "al-q-000676",
      "al-q-000962",
      "al-q-000689",
      "al-q-000586",
      "al-q-002112",
      "al-q-002129",
      "al-q-001862",
      "al-q-002126",
      "al-q-002843",
      "al-q-000878",
      "al-q-000342",
      "al-q-000399",
      "al-q-001299",
      "al-q-001048",
      "al-q-000808",
      "al-q-002484",
      "al-q-003138",
      "al-q-001335",
      "al-q-002771",
      "al-q-001324",
      "al-q-002859",
      "al-q-001856"
    ],
    "tags": [
      "题目自测"
    ],
    "updatedAt": "2026-07-03T00:00:00.000Z",
    "timeLimitMinutes": 60,
    "summary": "题目自测进阶",
    "description": "题目自测进阶",
    "slug": "题目自测进阶"
  },
  {
    "id": "al-exam-47",
    "title": "笔记总结进阶",
    "difficulty": "medium",
    "timeLimit": 60,
    "totalScore": 100,
    "passingScore": 60,
    "questionIds": [
      "al-q-001391",
      "al-q-003311",
      "al-q-000816",
      "al-q-001045",
      "al-q-001461",
      "al-q-001845",
      "al-q-001385",
      "al-q-003274",
      "al-q-000820",
      "al-q-002074",
      "al-q-002520",
      "al-q-003461",
      "al-q-000720",
      "al-q-002561",
      "al-q-002257",
      "al-q-001087",
      "al-q-001326",
      "al-q-000021",
      "al-q-002662",
      "al-q-002958",
      "al-q-002319",
      "al-q-002866",
      "al-q-003225",
      "al-q-000634",
      "al-q-002625"
    ],
    "tags": [
      "笔记总结"
    ],
    "updatedAt": "2026-07-03T00:00:00.000Z",
    "timeLimitMinutes": 60,
    "summary": "笔记总结进阶",
    "description": "笔记总结进阶",
    "slug": "笔记总结进阶"
  },
  {
    "id": "al-exam-48",
    "title": "编程辅助进阶",
    "difficulty": "medium",
    "timeLimit": 60,
    "totalScore": 100,
    "passingScore": 60,
    "questionIds": [
      "al-q-002148",
      "al-q-000551",
      "al-q-000344",
      "al-q-000175",
      "al-q-001330",
      "al-q-001612",
      "al-q-003222",
      "al-q-002829",
      "al-q-003373",
      "al-q-001779",
      "al-q-002598",
      "al-q-001074",
      "al-q-000761",
      "al-q-003457",
      "al-q-000488",
      "al-q-003002",
      "al-q-000145",
      "al-q-000011",
      "al-q-000503",
      "al-q-001460",
      "al-q-002591",
      "al-q-002433",
      "al-q-002750",
      "al-q-002994",
      "al-q-001247"
    ],
    "tags": [
      "编程辅助"
    ],
    "updatedAt": "2026-07-03T00:00:00.000Z",
    "timeLimitMinutes": 60,
    "summary": "编程辅助进阶",
    "description": "编程辅助进阶",
    "slug": "编程辅助进阶"
  },
  {
    "id": "al-exam-49",
    "title": "学科场景进阶",
    "difficulty": "medium",
    "timeLimit": 60,
    "totalScore": 100,
    "passingScore": 60,
    "questionIds": [
      "al-q-000735",
      "al-q-001085",
      "al-q-001720",
      "al-q-003224",
      "al-q-000197",
      "al-q-001226",
      "al-q-002292",
      "al-q-000050",
      "al-q-000427",
      "al-q-003256",
      "al-q-002255",
      "al-q-000564",
      "al-q-000082",
      "al-q-000075",
      "al-q-000995",
      "al-q-001261",
      "al-q-002923",
      "al-q-002769",
      "al-q-002533",
      "al-q-000251",
      "al-q-001728",
      "al-q-003045",
      "al-q-000494",
      "al-q-001700",
      "al-q-002444"
    ],
    "tags": [
      "学科场景"
    ],
    "updatedAt": "2026-07-03T00:00:00.000Z",
    "timeLimitMinutes": 60,
    "summary": "学科场景进阶",
    "description": "学科场景进阶",
    "slug": "学科场景进阶"
  },
  {
    "id": "al-exam-50",
    "title": "项目辅助进阶",
    "difficulty": "medium",
    "timeLimit": 60,
    "totalScore": 100,
    "passingScore": 60,
    "questionIds": [
      "al-q-003492",
      "al-q-000948",
      "al-q-003353",
      "al-q-001645",
      "al-q-000224",
      "al-q-002154",
      "al-q-002599",
      "al-q-002205",
      "al-q-000339",
      "al-q-000321",
      "al-q-001137",
      "al-q-002652",
      "al-q-002271",
      "al-q-000171",
      "al-q-001537",
      "al-q-000850",
      "al-q-001889",
      "al-q-003022",
      "al-q-002394",
      "al-q-001736",
      "al-q-001307",
      "al-q-001901",
      "al-q-000425",
      "al-q-001274",
      "al-q-002307"
    ],
    "tags": [
      "项目辅助"
    ],
    "updatedAt": "2026-07-03T00:00:00.000Z",
    "timeLimitMinutes": 60,
    "summary": "项目辅助进阶",
    "description": "项目辅助进阶",
    "slug": "项目辅助进阶"
  },
  {
    "id": "al-exam-51",
    "title": "事实核查进阶",
    "difficulty": "medium",
    "timeLimit": 60,
    "totalScore": 100,
    "passingScore": 60,
    "questionIds": [
      "al-q-001215",
      "al-q-002987",
      "al-q-003269",
      "al-q-000608",
      "al-q-001182",
      "al-q-001819",
      "al-q-001172",
      "al-q-002559",
      "al-q-000009",
      "al-q-000863",
      "al-q-003037",
      "al-q-002000",
      "al-q-001795",
      "al-q-002858",
      "al-q-002847",
      "al-q-002229",
      "al-q-002009",
      "al-q-002821",
      "al-q-001432",
      "al-q-001194",
      "al-q-003341",
      "al-q-001310",
      "al-q-003216",
      "al-q-000627",
      "al-q-002507"
    ],
    "tags": [
      "事实核查"
    ],
    "updatedAt": "2026-07-03T00:00:00.000Z",
    "timeLimitMinutes": 60,
    "summary": "事实核查进阶",
    "description": "事实核查进阶",
    "slug": "事实核查进阶"
  },
  {
    "id": "al-exam-52",
    "title": "工作流模板进阶",
    "difficulty": "medium",
    "timeLimit": 60,
    "totalScore": 100,
    "passingScore": 60,
    "questionIds": [
      "al-q-001042",
      "al-q-001723",
      "al-q-000377",
      "al-q-002369",
      "al-q-003313",
      "al-q-002809",
      "al-q-002776",
      "al-q-003105",
      "al-q-002523",
      "al-q-003048",
      "al-q-002389",
      "al-q-001565",
      "al-q-001158",
      "al-q-000388",
      "al-q-001828",
      "al-q-002895",
      "al-q-003182",
      "al-q-002517",
      "al-q-002748",
      "al-q-003175",
      "al-q-000386",
      "al-q-001797",
      "al-q-002558",
      "al-q-001467",
      "al-q-003131"
    ],
    "tags": [
      "工作流模板"
    ],
    "updatedAt": "2026-07-03T00:00:00.000Z",
    "timeLimitMinutes": 60,
    "summary": "工作流模板进阶",
    "description": "工作流模板进阶",
    "slug": "工作流模板进阶"
  },
  {
    "id": "al-exam-53",
    "title": "学习日志进阶",
    "difficulty": "medium",
    "timeLimit": 60,
    "totalScore": 100,
    "passingScore": 60,
    "questionIds": [
      "al-q-000582",
      "al-q-003039",
      "al-q-003174",
      "al-q-000142",
      "al-q-002755",
      "al-q-000774",
      "al-q-001122",
      "al-q-002951",
      "al-q-002947",
      "al-q-002276",
      "al-q-000200",
      "al-q-000884",
      "al-q-002386",
      "al-q-002920",
      "al-q-001416",
      "al-q-003497",
      "al-q-002644",
      "al-q-000331",
      "al-q-002887",
      "al-q-000665",
      "al-q-001526",
      "al-q-002098",
      "al-q-000632",
      "al-q-000794",
      "al-q-002587"
    ],
    "tags": [
      "学习日志"
    ],
    "updatedAt": "2026-07-03T00:00:00.000Z",
    "timeLimitMinutes": 60,
    "summary": "学习日志进阶",
    "description": "学习日志进阶",
    "slug": "学习日志进阶"
  },
  {
    "id": "al-exam-54",
    "title": "输出评估进阶",
    "difficulty": "medium",
    "timeLimit": 60,
    "totalScore": 100,
    "passingScore": 60,
    "questionIds": [
      "al-q-002347",
      "al-q-003190",
      "al-q-002849",
      "al-q-000554",
      "al-q-001763",
      "al-q-000823",
      "al-q-000721",
      "al-q-001834",
      "al-q-000387",
      "al-q-001982",
      "al-q-000482",
      "al-q-002181",
      "al-q-001144",
      "al-q-000174",
      "al-q-000915",
      "al-q-000726",
      "al-q-002192",
      "al-q-001539",
      "al-q-000285",
      "al-q-000786",
      "al-q-003130",
      "al-q-003423",
      "al-q-002798",
      "al-q-000883",
      "al-q-000037"
    ],
    "tags": [
      "输出评估"
    ],
    "updatedAt": "2026-07-03T00:00:00.000Z",
    "timeLimitMinutes": 60,
    "summary": "输出评估进阶",
    "description": "输出评估进阶",
    "slug": "输出评估进阶"
  },
  {
    "id": "al-exam-55",
    "title": "安全规范进阶",
    "difficulty": "medium",
    "timeLimit": 60,
    "totalScore": 100,
    "passingScore": 60,
    "questionIds": [
      "al-q-003435",
      "al-q-001464",
      "al-q-002430",
      "al-q-000670",
      "al-q-000166",
      "al-q-001883",
      "al-q-000770",
      "al-q-003412",
      "al-q-002564",
      "al-q-003297",
      "al-q-001178",
      "al-q-003096",
      "al-q-001043",
      "al-q-002965",
      "al-q-000926",
      "al-q-001221",
      "al-q-000232",
      "al-q-001500",
      "al-q-003364",
      "al-q-000189",
      "al-q-001669",
      "al-q-002638",
      "al-q-001621",
      "al-q-003350",
      "al-q-003088"
    ],
    "tags": [
      "安全规范"
    ],
    "updatedAt": "2026-07-03T00:00:00.000Z",
    "timeLimitMinutes": 60,
    "summary": "安全规范进阶",
    "description": "安全规范进阶",
    "slug": "安全规范进阶"
  },
  {
    "id": "al-exam-56",
    "title": "AI综合进阶",
    "difficulty": "medium",
    "timeLimit": 60,
    "totalScore": 100,
    "passingScore": 60,
    "questionIds": [
      "al-q-002396",
      "al-q-001319",
      "al-q-001936",
      "al-q-001375",
      "al-q-000845",
      "al-q-001796",
      "al-q-003213",
      "al-q-001506",
      "al-q-000710",
      "al-q-000300",
      "al-q-002840",
      "al-q-002134",
      "al-q-000299",
      "al-q-002491",
      "al-q-000840",
      "al-q-001282",
      "al-q-002572",
      "al-q-001222",
      "al-q-002694",
      "al-q-000249",
      "al-q-002854",
      "al-q-001970",
      "al-q-001312",
      "al-q-001320",
      "al-q-002460"
    ],
    "tags": [
      "AI综合"
    ],
    "updatedAt": "2026-07-03T00:00:00.000Z",
    "timeLimitMinutes": 60,
    "summary": "AI综合进阶",
    "description": "AI综合进阶",
    "slug": "ai综合进阶"
  },
  {
    "id": "al-exam-57",
    "title": "AI入门进阶",
    "difficulty": "medium",
    "timeLimit": 60,
    "totalScore": 100,
    "passingScore": 60,
    "questionIds": [
      "al-q-003076",
      "al-q-002515",
      "al-q-001775",
      "al-q-002109",
      "al-q-000983",
      "al-q-000834",
      "al-q-000620",
      "al-q-000406",
      "al-q-000577",
      "al-q-001852",
      "al-q-000951",
      "al-q-000086",
      "al-q-000042",
      "al-q-000498",
      "al-q-000560",
      "al-q-000604",
      "al-q-001253",
      "al-q-002695",
      "al-q-003441",
      "al-q-002527",
      "al-q-001615",
      "al-q-001184",
      "al-q-001551",
      "al-q-002600",
      "al-q-001620"
    ],
    "tags": [
      "AI入门"
    ],
    "updatedAt": "2026-07-03T00:00:00.000Z",
    "timeLimitMinutes": 60,
    "summary": "AI入门进阶",
    "description": "AI入门进阶",
    "slug": "ai入门进阶"
  },
  {
    "id": "al-exam-58",
    "title": "学习计划进阶",
    "difficulty": "medium",
    "timeLimit": 60,
    "totalScore": 100,
    "passingScore": 60,
    "questionIds": [
      "al-q-000697",
      "al-q-001532",
      "al-q-002211",
      "al-q-003093",
      "al-q-002281",
      "al-q-002479",
      "al-q-000101",
      "al-q-002582",
      "al-q-002953",
      "al-q-001570",
      "al-q-001041",
      "al-q-003374",
      "al-q-000484",
      "al-q-001725",
      "al-q-003058",
      "al-q-000752",
      "al-q-000208",
      "al-q-000303",
      "al-q-001963",
      "al-q-003329",
      "al-q-001957",
      "al-q-001071",
      "al-q-000499",
      "al-q-000326",
      "al-q-002666"
    ],
    "tags": [
      "学习计划"
    ],
    "updatedAt": "2026-07-03T00:00:00.000Z",
    "timeLimitMinutes": 60,
    "summary": "学习计划进阶",
    "description": "学习计划进阶",
    "slug": "学习计划进阶"
  },
  {
    "id": "al-exam-59",
    "title": "知识解释进阶",
    "difficulty": "medium",
    "timeLimit": 60,
    "totalScore": 100,
    "passingScore": 60,
    "questionIds": [
      "al-q-001283",
      "al-q-001784",
      "al-q-000886",
      "al-q-003111",
      "al-q-003448",
      "al-q-002231",
      "al-q-002075",
      "al-q-002930",
      "al-q-002664",
      "al-q-000522",
      "al-q-000437",
      "al-q-002516",
      "al-q-000370",
      "al-q-001756",
      "al-q-001354",
      "al-q-001688",
      "al-q-003181",
      "al-q-000656",
      "al-q-001387",
      "al-q-001721",
      "al-q-001400",
      "al-q-002217",
      "al-q-002246",
      "al-q-001114",
      "al-q-002733"
    ],
    "tags": [
      "知识解释"
    ],
    "updatedAt": "2026-07-03T00:00:00.000Z",
    "timeLimitMinutes": 60,
    "summary": "知识解释进阶",
    "description": "知识解释进阶",
    "slug": "知识解释进阶"
  },
  {
    "id": "al-exam-60",
    "title": "题目自测进阶",
    "difficulty": "medium",
    "timeLimit": 60,
    "totalScore": 100,
    "passingScore": 60,
    "questionIds": [
      "al-q-001202",
      "al-q-000878",
      "al-q-003454",
      "al-q-001363",
      "al-q-002127",
      "al-q-000689",
      "al-q-002258",
      "al-q-001503",
      "al-q-001994",
      "al-q-003295",
      "al-q-001531",
      "al-q-001764",
      "al-q-002456",
      "al-q-000477",
      "al-q-000909",
      "al-q-001285",
      "al-q-003272",
      "al-q-002907",
      "al-q-002751",
      "al-q-001214",
      "al-q-003188",
      "al-q-002206",
      "al-q-003169",
      "al-q-001991",
      "al-q-001269"
    ],
    "tags": [
      "题目自测"
    ],
    "updatedAt": "2026-07-03T00:00:00.000Z",
    "timeLimitMinutes": 60,
    "summary": "题目自测进阶",
    "description": "题目自测进阶",
    "slug": "题目自测进阶"
  },
  {
    "id": "al-exam-61",
    "title": "笔记总结进阶",
    "difficulty": "medium",
    "timeLimit": 60,
    "totalScore": 100,
    "passingScore": 60,
    "questionIds": [
      "al-q-000921",
      "al-q-002831",
      "al-q-001391",
      "al-q-002674",
      "al-q-002931",
      "al-q-002978",
      "al-q-000222",
      "al-q-003430",
      "al-q-001461",
      "al-q-000447",
      "al-q-000192",
      "al-q-000413",
      "al-q-001703",
      "al-q-001136",
      "al-q-002228",
      "al-q-002747",
      "al-q-002007",
      "al-q-000839",
      "al-q-001788",
      "al-q-002804",
      "al-q-002121",
      "al-q-001746",
      "al-q-001825",
      "al-q-000635",
      "al-q-000743"
    ],
    "tags": [
      "笔记总结"
    ],
    "updatedAt": "2026-07-03T00:00:00.000Z",
    "timeLimitMinutes": 60,
    "summary": "笔记总结进阶",
    "description": "笔记总结进阶",
    "slug": "笔记总结进阶"
  },
  {
    "id": "al-exam-62",
    "title": "编程辅助进阶",
    "difficulty": "medium",
    "timeLimit": 60,
    "totalScore": 100,
    "passingScore": 60,
    "questionIds": [
      "al-q-002031",
      "al-q-001295",
      "al-q-001707",
      "al-q-000317",
      "al-q-002193",
      "al-q-002442",
      "al-q-000022",
      "al-q-000645",
      "al-q-002602",
      "al-q-002334",
      "al-q-001247",
      "al-q-002102",
      "al-q-003106",
      "al-q-000488",
      "al-q-001663",
      "al-q-001892",
      "al-q-003259",
      "al-q-001435",
      "al-q-000093",
      "al-q-001810",
      "al-q-001190",
      "al-q-003021",
      "al-q-003286",
      "al-q-003019",
      "al-q-000318"
    ],
    "tags": [
      "编程辅助"
    ],
    "updatedAt": "2026-07-03T00:00:00.000Z",
    "timeLimitMinutes": 60,
    "summary": "编程辅助进阶",
    "description": "编程辅助进阶",
    "slug": "编程辅助进阶"
  },
  {
    "id": "al-exam-63",
    "title": "学科场景进阶",
    "difficulty": "medium",
    "timeLimit": 60,
    "totalScore": 100,
    "passingScore": 60,
    "questionIds": [
      "al-q-001481",
      "al-q-003224",
      "al-q-001697",
      "al-q-002499",
      "al-q-001700",
      "al-q-000768",
      "al-q-001183",
      "al-q-000818",
      "al-q-003395",
      "al-q-000186",
      "al-q-001226",
      "al-q-000427",
      "al-q-001778",
      "al-q-003212",
      "al-q-003202",
      "al-q-001197",
      "al-q-003414",
      "al-q-000271",
      "al-q-003161",
      "al-q-001648",
      "al-q-001744",
      "al-q-002686",
      "al-q-001085",
      "al-q-003312",
      "al-q-000251"
    ],
    "tags": [
      "学科场景"
    ],
    "updatedAt": "2026-07-03T00:00:00.000Z",
    "timeLimitMinutes": 60,
    "summary": "学科场景进阶",
    "description": "学科场景进阶",
    "slug": "学科场景进阶"
  },
  {
    "id": "al-exam-64",
    "title": "项目辅助进阶",
    "difficulty": "medium",
    "timeLimit": 60,
    "totalScore": 100,
    "passingScore": 60,
    "questionIds": [
      "al-q-000053",
      "al-q-001446",
      "al-q-000873",
      "al-q-001465",
      "al-q-002218",
      "al-q-001925",
      "al-q-000672",
      "al-q-001917",
      "al-q-000080",
      "al-q-001591",
      "al-q-001490",
      "al-q-003336",
      "al-q-002764",
      "al-q-001736",
      "al-q-001223",
      "al-q-000052",
      "al-q-003073",
      "al-q-002616",
      "al-q-001893",
      "al-q-002016",
      "al-q-001260",
      "al-q-000072",
      "al-q-002059",
      "al-q-000457",
      "al-q-002874"
    ],
    "tags": [
      "项目辅助"
    ],
    "updatedAt": "2026-07-03T00:00:00.000Z",
    "timeLimitMinutes": 60,
    "summary": "项目辅助进阶",
    "description": "项目辅助进阶",
    "slug": "项目辅助进阶"
  },
  {
    "id": "al-exam-65",
    "title": "事实核查进阶",
    "difficulty": "medium",
    "timeLimit": 60,
    "totalScore": 100,
    "passingScore": 60,
    "questionIds": [
      "al-q-001172",
      "al-q-001494",
      "al-q-000548",
      "al-q-002406",
      "al-q-002637",
      "al-q-002670",
      "al-q-001628",
      "al-q-003269",
      "al-q-001414",
      "al-q-001514",
      "al-q-000608",
      "al-q-002902",
      "al-q-000813",
      "al-q-000931",
      "al-q-002381",
      "al-q-001407",
      "al-q-000546",
      "al-q-002676",
      "al-q-001362",
      "al-q-001749",
      "al-q-001819",
      "al-q-003128",
      "al-q-002571",
      "al-q-001039",
      "al-q-002436"
    ],
    "tags": [
      "事实核查"
    ],
    "updatedAt": "2026-07-03T00:00:00.000Z",
    "timeLimitMinutes": 60,
    "summary": "事实核查进阶",
    "description": "事实核查进阶",
    "slug": "事实核查进阶"
  },
  {
    "id": "al-exam-66",
    "title": "工作流模板进阶",
    "difficulty": "hard",
    "timeLimit": 60,
    "totalScore": 100,
    "passingScore": 60,
    "questionIds": [
      "al-q-002369",
      "al-q-003109",
      "al-q-001754",
      "al-q-000081",
      "al-q-000263",
      "al-q-002691",
      "al-q-000230",
      "al-q-001747",
      "al-q-000599",
      "al-q-002995",
      "al-q-001086",
      "al-q-002748",
      "al-q-002963",
      "al-q-001141",
      "al-q-002888",
      "al-q-002133",
      "al-q-000988",
      "al-q-002845",
      "al-q-000978",
      "al-q-000644",
      "al-q-001360",
      "al-q-002077",
      "al-q-002726",
      "al-q-003112",
      "al-q-000699"
    ],
    "tags": [
      "工作流模板"
    ],
    "updatedAt": "2026-07-03T00:00:00.000Z",
    "timeLimitMinutes": 60,
    "summary": "工作流模板进阶",
    "description": "工作流模板进阶",
    "slug": "工作流模板进阶"
  },
  {
    "id": "al-exam-67",
    "title": "学习日志进阶",
    "difficulty": "hard",
    "timeLimit": 60,
    "totalScore": 100,
    "passingScore": 60,
    "questionIds": [
      "al-q-002850",
      "al-q-000431",
      "al-q-000137",
      "al-q-000417",
      "al-q-000500",
      "al-q-000468",
      "al-q-000934",
      "al-q-000229",
      "al-q-003174",
      "al-q-000198",
      "al-q-001498",
      "al-q-002636",
      "al-q-000298",
      "al-q-001557",
      "al-q-000648",
      "al-q-000039",
      "al-q-002524",
      "al-q-002366",
      "al-q-002879",
      "al-q-000830",
      "al-q-001291",
      "al-q-000748",
      "al-q-002905",
      "al-q-001345",
      "al-q-000375"
    ],
    "tags": [
      "学习日志"
    ],
    "updatedAt": "2026-07-03T00:00:00.000Z",
    "timeLimitMinutes": 60,
    "summary": "学习日志进阶",
    "description": "学习日志进阶",
    "slug": "学习日志进阶"
  },
  {
    "id": "al-exam-68",
    "title": "输出评估进阶",
    "difficulty": "hard",
    "timeLimit": 60,
    "totalScore": 100,
    "passingScore": 60,
    "questionIds": [
      "al-q-002505",
      "al-q-002180",
      "al-q-000211",
      "al-q-002226",
      "al-q-001993",
      "al-q-001277",
      "al-q-000474",
      "al-q-001660",
      "al-q-002913",
      "al-q-003223",
      "al-q-002192",
      "al-q-001982",
      "al-q-000933",
      "al-q-002838",
      "al-q-003052",
      "al-q-000524",
      "al-q-000430",
      "al-q-000603",
      "al-q-001972",
      "al-q-000037",
      "al-q-002894",
      "al-q-003380",
      "al-q-001051",
      "al-q-002786",
      "al-q-002044"
    ],
    "tags": [
      "输出评估"
    ],
    "updatedAt": "2026-07-03T00:00:00.000Z",
    "timeLimitMinutes": 60,
    "summary": "输出评估进阶",
    "description": "输出评估进阶",
    "slug": "输出评估进阶"
  },
  {
    "id": "al-exam-69",
    "title": "安全规范进阶",
    "difficulty": "hard",
    "timeLimit": 60,
    "totalScore": 100,
    "passingScore": 60,
    "questionIds": [
      "al-q-000937",
      "al-q-003244",
      "al-q-003466",
      "al-q-002388",
      "al-q-001044",
      "al-q-000543",
      "al-q-002513",
      "al-q-000136",
      "al-q-001883",
      "al-q-000203",
      "al-q-002710",
      "al-q-000891",
      "al-q-002390",
      "al-q-000473",
      "al-q-001923",
      "al-q-002509",
      "al-q-002792",
      "al-q-002754",
      "al-q-000141",
      "al-q-000976",
      "al-q-001340",
      "al-q-003412",
      "al-q-002117",
      "al-q-000968",
      "al-q-000511"
    ],
    "tags": [
      "安全规范"
    ],
    "updatedAt": "2026-07-03T00:00:00.000Z",
    "timeLimitMinutes": 60,
    "summary": "安全规范进阶",
    "description": "安全规范进阶",
    "slug": "安全规范进阶"
  },
  {
    "id": "al-exam-70",
    "title": "AI综合进阶",
    "difficulty": "hard",
    "timeLimit": 60,
    "totalScore": 100,
    "passingScore": 60,
    "questionIds": [
      "al-q-001796",
      "al-q-003041",
      "al-q-003328",
      "al-q-001325",
      "al-q-001680",
      "al-q-003059",
      "al-q-000870",
      "al-q-001124",
      "al-q-001222",
      "al-q-000135",
      "al-q-000651",
      "al-q-003292",
      "al-q-001282",
      "al-q-002928",
      "al-q-002249",
      "al-q-001558",
      "al-q-002961",
      "al-q-002563",
      "al-q-003209",
      "al-q-001737",
      "al-q-002656",
      "al-q-000835",
      "al-q-003275",
      "al-q-002655",
      "al-q-000736"
    ],
    "tags": [
      "AI综合"
    ],
    "updatedAt": "2026-07-03T00:00:00.000Z",
    "timeLimitMinutes": 60,
    "summary": "AI综合进阶",
    "description": "AI综合进阶",
    "slug": "ai综合进阶"
  },
  {
    "id": "al-exam-71",
    "title": "AI入门进阶",
    "difficulty": "hard",
    "timeLimit": 60,
    "totalScore": 100,
    "passingScore": 60,
    "questionIds": [
      "al-q-002739",
      "al-q-002299",
      "al-q-002936",
      "al-q-003474",
      "al-q-001095",
      "al-q-000026",
      "al-q-002927",
      "al-q-002688",
      "al-q-000042",
      "al-q-000533",
      "al-q-002268",
      "al-q-003402",
      "al-q-002478",
      "al-q-001091",
      "al-q-002324",
      "al-q-000505",
      "al-q-000443",
      "al-q-000498",
      "al-q-002526",
      "al-q-003010",
      "al-q-002749",
      "al-q-000775",
      "al-q-002177",
      "al-q-001975",
      "al-q-001651"
    ],
    "tags": [
      "AI入门"
    ],
    "updatedAt": "2026-07-03T00:00:00.000Z",
    "timeLimitMinutes": 60,
    "summary": "AI入门进阶",
    "description": "AI入门进阶",
    "slug": "ai入门进阶"
  },
  {
    "id": "al-exam-72",
    "title": "学习计划进阶",
    "difficulty": "hard",
    "timeLimit": 60,
    "totalScore": 100,
    "passingScore": 60,
    "questionIds": [
      "al-q-002772",
      "al-q-001082",
      "al-q-000322",
      "al-q-002666",
      "al-q-000310",
      "al-q-000389",
      "al-q-001584",
      "al-q-001701",
      "al-q-001296",
      "al-q-000499",
      "al-q-001689",
      "al-q-000900",
      "al-q-003238",
      "al-q-000258",
      "al-q-001418",
      "al-q-003043",
      "al-q-000696",
      "al-q-001200",
      "al-q-001073",
      "al-q-001544",
      "al-q-002141",
      "al-q-001928",
      "al-q-002269",
      "al-q-000647",
      "al-q-000843"
    ],
    "tags": [
      "学习计划"
    ],
    "updatedAt": "2026-07-03T00:00:00.000Z",
    "timeLimitMinutes": 60,
    "summary": "学习计划进阶",
    "description": "学习计划进阶",
    "slug": "学习计划进阶"
  },
  {
    "id": "al-exam-73",
    "title": "知识解释进阶",
    "difficulty": "hard",
    "timeLimit": 60,
    "totalScore": 100,
    "passingScore": 60,
    "questionIds": [
      "al-q-001230",
      "al-q-000886",
      "al-q-000162",
      "al-q-000797",
      "al-q-000237",
      "al-q-001813",
      "al-q-002034",
      "al-q-002393",
      "al-q-002982",
      "al-q-003356",
      "al-q-003496",
      "al-q-001114",
      "al-q-002461",
      "al-q-003181",
      "al-q-000373",
      "al-q-001784",
      "al-q-002930",
      "al-q-002624",
      "al-q-002336",
      "al-q-001756",
      "al-q-001387",
      "al-q-000257",
      "al-q-002217",
      "al-q-000687",
      "al-q-002093"
    ],
    "tags": [
      "知识解释"
    ],
    "updatedAt": "2026-07-03T00:00:00.000Z",
    "timeLimitMinutes": 60,
    "summary": "知识解释进阶",
    "description": "知识解释进阶",
    "slug": "知识解释进阶"
  },
  {
    "id": "al-exam-74",
    "title": "题目自测进阶",
    "difficulty": "hard",
    "timeLimit": 60,
    "totalScore": 100,
    "passingScore": 60,
    "questionIds": [
      "al-q-002209",
      "al-q-002060",
      "al-q-000238",
      "al-q-000004",
      "al-q-002126",
      "al-q-001424",
      "al-q-000814",
      "al-q-001081",
      "al-q-002073",
      "al-q-002635",
      "al-q-001258",
      "al-q-000342",
      "al-q-002634",
      "al-q-001659",
      "al-q-001661",
      "al-q-001168",
      "al-q-002085",
      "al-q-003006",
      "al-q-001125",
      "al-q-002863",
      "al-q-001214",
      "al-q-001047",
      "al-q-002488",
      "al-q-002300",
      "al-q-002907"
    ],
    "tags": [
      "题目自测"
    ],
    "updatedAt": "2026-07-03T00:00:00.000Z",
    "timeLimitMinutes": 60,
    "summary": "题目自测进阶",
    "description": "题目自测进阶",
    "slug": "题目自测进阶"
  },
  {
    "id": "al-exam-75",
    "title": "笔记总结进阶",
    "difficulty": "hard",
    "timeLimit": 60,
    "totalScore": 100,
    "passingScore": 60,
    "questionIds": [
      "al-q-000624",
      "al-q-000723",
      "al-q-001962",
      "al-q-003433",
      "al-q-002120",
      "al-q-000882",
      "al-q-003145",
      "al-q-002931",
      "al-q-001687",
      "al-q-002911",
      "al-q-001488",
      "al-q-000831",
      "al-q-002687",
      "al-q-001161",
      "al-q-001853",
      "al-q-002830",
      "al-q-002301",
      "al-q-003279",
      "al-q-003239",
      "al-q-001208",
      "al-q-000852",
      "al-q-002254",
      "al-q-002306",
      "al-q-000921",
      "al-q-001289"
    ],
    "tags": [
      "笔记总结"
    ],
    "updatedAt": "2026-07-03T00:00:00.000Z",
    "timeLimitMinutes": 60,
    "summary": "笔记总结进阶",
    "description": "笔记总结进阶",
    "slug": "笔记总结进阶"
  },
  {
    "id": "al-exam-76",
    "title": "编程辅助进阶",
    "difficulty": "hard",
    "timeLimit": 60,
    "totalScore": 100,
    "passingScore": 60,
    "questionIds": [
      "al-q-000960",
      "al-q-003456",
      "al-q-002284",
      "al-q-003050",
      "al-q-001308",
      "al-q-002713",
      "al-q-000466",
      "al-q-000400",
      "al-q-000093",
      "al-q-002800",
      "al-q-002128",
      "al-q-002598",
      "al-q-000645",
      "al-q-003019",
      "al-q-000692",
      "al-q-001911",
      "al-q-001857",
      "al-q-003345",
      "al-q-000858",
      "al-q-003106",
      "al-q-002368",
      "al-q-003326",
      "al-q-000378",
      "al-q-001410",
      "al-q-000778"
    ],
    "tags": [
      "编程辅助"
    ],
    "updatedAt": "2026-07-03T00:00:00.000Z",
    "timeLimitMinutes": 60,
    "summary": "编程辅助进阶",
    "description": "编程辅助进阶",
    "slug": "编程辅助进阶"
  },
  {
    "id": "al-exam-77",
    "title": "学科场景进阶",
    "difficulty": "hard",
    "timeLimit": 60,
    "totalScore": 100,
    "passingScore": 60,
    "questionIds": [
      "al-q-001778",
      "al-q-002340",
      "al-q-000458",
      "al-q-002119",
      "al-q-001757",
      "al-q-001791",
      "al-q-002404",
      "al-q-001684",
      "al-q-000733",
      "al-q-001790",
      "al-q-000091",
      "al-q-001768",
      "al-q-001780",
      "al-q-001077",
      "al-q-001183",
      "al-q-002468",
      "al-q-001348",
      "al-q-001984",
      "al-q-000732",
      "al-q-001270",
      "al-q-000871",
      "al-q-003395",
      "al-q-003372",
      "al-q-002698",
      "al-q-000751"
    ],
    "tags": [
      "学科场景"
    ],
    "updatedAt": "2026-07-03T00:00:00.000Z",
    "timeLimitMinutes": 60,
    "summary": "学科场景进阶",
    "description": "学科场景进阶",
    "slug": "学科场景进阶"
  },
  {
    "id": "al-exam-78",
    "title": "项目辅助进阶",
    "difficulty": "hard",
    "timeLimit": 60,
    "totalScore": 100,
    "passingScore": 60,
    "questionIds": [
      "al-q-001447",
      "al-q-001695",
      "al-q-000467",
      "al-q-000713",
      "al-q-001211",
      "al-q-001278",
      "al-q-002734",
      "al-q-002027",
      "al-q-002901",
      "al-q-002023",
      "al-q-001632",
      "al-q-002312",
      "al-q-000829",
      "al-q-000532",
      "al-q-000383",
      "al-q-000574",
      "al-q-003159",
      "al-q-001590",
      "al-q-002047",
      "al-q-003409",
      "al-q-001165",
      "al-q-002116",
      "al-q-002307",
      "al-q-000008",
      "al-q-000555"
    ],
    "tags": [
      "项目辅助"
    ],
    "updatedAt": "2026-07-03T00:00:00.000Z",
    "timeLimitMinutes": 60,
    "summary": "项目辅助进阶",
    "description": "项目辅助进阶",
    "slug": "项目辅助进阶"
  },
  {
    "id": "al-exam-79",
    "title": "事实核查进阶",
    "difficulty": "hard",
    "timeLimit": 60,
    "totalScore": 100,
    "passingScore": 60,
    "questionIds": [
      "al-q-003217",
      "al-q-002285",
      "al-q-003033",
      "al-q-002534",
      "al-q-001818",
      "al-q-000146",
      "al-q-002485",
      "al-q-000548",
      "al-q-000868",
      "al-q-000627",
      "al-q-002470",
      "al-q-001206",
      "al-q-001795",
      "al-q-001037",
      "al-q-002683",
      "al-q-002777",
      "al-q-000272",
      "al-q-002003",
      "al-q-002019",
      "al-q-000114",
      "al-q-003365",
      "al-q-001020",
      "al-q-002571",
      "al-q-001520",
      "al-q-002095"
    ],
    "tags": [
      "事实核查"
    ],
    "updatedAt": "2026-07-03T00:00:00.000Z",
    "timeLimitMinutes": 60,
    "summary": "事实核查进阶",
    "description": "事实核查进阶",
    "slug": "事实核查进阶"
  },
  {
    "id": "al-exam-80",
    "title": "工作流模板进阶",
    "difficulty": "hard",
    "timeLimit": 60,
    "totalScore": 100,
    "passingScore": 60,
    "questionIds": [
      "al-q-002486",
      "al-q-002921",
      "al-q-000485",
      "al-q-001023",
      "al-q-002050",
      "al-q-000902",
      "al-q-003250",
      "al-q-003081",
      "al-q-001851",
      "al-q-001727",
      "al-q-000599",
      "al-q-002613",
      "al-q-002691",
      "al-q-000756",
      "al-q-001811",
      "al-q-000081",
      "al-q-001510",
      "al-q-003383",
      "al-q-003315",
      "al-q-003113",
      "al-q-001890",
      "al-q-003340",
      "al-q-000847",
      "al-q-000596",
      "al-q-002389"
    ],
    "tags": [
      "工作流模板"
    ],
    "updatedAt": "2026-07-03T00:00:00.000Z",
    "timeLimitMinutes": 60,
    "summary": "工作流模板进阶",
    "description": "工作流模板进阶",
    "slug": "工作流模板进阶"
  },
  {
    "id": "al-exam-81",
    "title": "学习日志进阶",
    "difficulty": "hard",
    "timeLimit": 60,
    "totalScore": 100,
    "passingScore": 60,
    "questionIds": [
      "al-q-002418",
      "al-q-003253",
      "al-q-001492",
      "al-q-002569",
      "al-q-000431",
      "al-q-000632",
      "al-q-003389",
      "al-q-000854",
      "al-q-000582",
      "al-q-002887",
      "al-q-003428",
      "al-q-000242",
      "al-q-000890",
      "al-q-003242",
      "al-q-002017",
      "al-q-001291",
      "al-q-000952",
      "al-q-000307",
      "al-q-002030",
      "al-q-000722",
      "al-q-002814",
      "al-q-001718",
      "al-q-002969",
      "al-q-002951",
      "al-q-001345"
    ],
    "tags": [
      "学习日志"
    ],
    "updatedAt": "2026-07-03T00:00:00.000Z",
    "timeLimitMinutes": 60,
    "summary": "学习日志进阶",
    "description": "学习日志进阶",
    "slug": "学习日志进阶"
  },
  {
    "id": "al-exam-82",
    "title": "输出评估进阶",
    "difficulty": "hard",
    "timeLimit": 60,
    "totalScore": 100,
    "passingScore": 60,
    "questionIds": [
      "al-q-003468",
      "al-q-003376",
      "al-q-002395",
      "al-q-003463",
      "al-q-002862",
      "al-q-001403",
      "al-q-000054",
      "al-q-000887",
      "al-q-001660",
      "al-q-001706",
      "al-q-001972",
      "al-q-001102",
      "al-q-002917",
      "al-q-001309",
      "al-q-002906",
      "al-q-000918",
      "al-q-000998",
      "al-q-000786",
      "al-q-002238",
      "al-q-000481",
      "al-q-000060",
      "al-q-002505",
      "al-q-000111",
      "al-q-003303",
      "al-q-001530"
    ],
    "tags": [
      "输出评估"
    ],
    "updatedAt": "2026-07-03T00:00:00.000Z",
    "timeLimitMinutes": 60,
    "summary": "输出评估进阶",
    "description": "输出评估进阶",
    "slug": "输出评估进阶"
  },
  {
    "id": "al-exam-83",
    "title": "安全规范进阶",
    "difficulty": "hard",
    "timeLimit": 60,
    "totalScore": 100,
    "passingScore": 60,
    "questionIds": [
      "al-q-001496",
      "al-q-001032",
      "al-q-001500",
      "al-q-002342",
      "al-q-002117",
      "al-q-001221",
      "al-q-002754",
      "al-q-001070",
      "al-q-002685",
      "al-q-003369",
      "al-q-001099",
      "al-q-001653",
      "al-q-003485",
      "al-q-002823",
      "al-q-003494",
      "al-q-003200",
      "al-q-000284",
      "al-q-003394",
      "al-q-000061",
      "al-q-002032",
      "al-q-001824",
      "al-q-002171",
      "al-q-000396",
      "al-q-002661",
      "al-q-002207"
    ],
    "tags": [
      "安全规范"
    ],
    "updatedAt": "2026-07-03T00:00:00.000Z",
    "timeLimitMinutes": 60,
    "summary": "安全规范进阶",
    "description": "安全规范进阶",
    "slug": "安全规范进阶"
  },
  {
    "id": "al-exam-84",
    "title": "AI综合进阶",
    "difficulty": "hard",
    "timeLimit": 60,
    "totalScore": 100,
    "passingScore": 60,
    "questionIds": [
      "al-q-002363",
      "al-q-002966",
      "al-q-002453",
      "al-q-002840",
      "al-q-001614",
      "al-q-002502",
      "al-q-000587",
      "al-q-000196",
      "al-q-003243",
      "al-q-001439",
      "al-q-001709",
      "al-q-001558",
      "al-q-000835",
      "al-q-000244",
      "al-q-000249",
      "al-q-003382",
      "al-q-003377",
      "al-q-001879",
      "al-q-001353",
      "al-q-003040",
      "al-q-002232",
      "al-q-001135",
      "al-q-002215",
      "al-q-000410",
      "al-q-003195"
    ],
    "tags": [
      "AI综合"
    ],
    "updatedAt": "2026-07-03T00:00:00.000Z",
    "timeLimitMinutes": 60,
    "summary": "AI综合进阶",
    "description": "AI综合进阶",
    "slug": "ai综合进阶"
  },
  {
    "id": "al-exam-85",
    "title": "AI入门进阶",
    "difficulty": "hard",
    "timeLimit": 60,
    "totalScore": 100,
    "passingScore": 60,
    "questionIds": [
      "al-q-002812",
      "al-q-000406",
      "al-q-002739",
      "al-q-000374",
      "al-q-002252",
      "al-q-002757",
      "al-q-000042",
      "al-q-001466",
      "al-q-002525",
      "al-q-001775",
      "al-q-001740",
      "al-q-001063",
      "al-q-000690",
      "al-q-000356",
      "al-q-001753",
      "al-q-002936",
      "al-q-000505",
      "al-q-000191",
      "al-q-000544",
      "al-q-000421",
      "al-q-000295",
      "al-q-002179",
      "al-q-001339",
      "al-q-002273",
      "al-q-002012"
    ],
    "tags": [
      "AI入门"
    ],
    "updatedAt": "2026-07-03T00:00:00.000Z",
    "timeLimitMinutes": 60,
    "summary": "AI入门进阶",
    "description": "AI入门进阶",
    "slug": "ai入门进阶"
  },
  {
    "id": "al-exam-86",
    "title": "学习计划进阶",
    "difficulty": "hard",
    "timeLimit": 60,
    "totalScore": 100,
    "passingScore": 60,
    "questionIds": [
      "al-q-003446",
      "al-q-002784",
      "al-q-000625",
      "al-q-001480",
      "al-q-001957",
      "al-q-002714",
      "al-q-001820",
      "al-q-003469",
      "al-q-001802",
      "al-q-002002",
      "al-q-002885",
      "al-q-001946",
      "al-q-001355",
      "al-q-000094",
      "al-q-002269",
      "al-q-001209",
      "al-q-002991",
      "al-q-002666",
      "al-q-001997",
      "al-q-000372",
      "al-q-000138",
      "al-q-001082",
      "al-q-000752",
      "al-q-002972",
      "al-q-003144"
    ],
    "tags": [
      "学习计划"
    ],
    "updatedAt": "2026-07-03T00:00:00.000Z",
    "timeLimitMinutes": 60,
    "summary": "学习计划进阶",
    "description": "学习计划进阶",
    "slug": "学习计划进阶"
  },
  {
    "id": "al-exam-87",
    "title": "知识解释进阶",
    "difficulty": "hard",
    "timeLimit": 60,
    "totalScore": 100,
    "passingScore": 60,
    "questionIds": [
      "al-q-001605",
      "al-q-002282",
      "al-q-002729",
      "al-q-002930",
      "al-q-003378",
      "al-q-002048",
      "al-q-002664",
      "al-q-000154",
      "al-q-000162",
      "al-q-001550",
      "al-q-001463",
      "al-q-002178",
      "al-q-000999",
      "al-q-001283",
      "al-q-003228",
      "al-q-003176",
      "al-q-002546",
      "al-q-000957",
      "al-q-002733",
      "al-q-002744",
      "al-q-002360",
      "al-q-002469",
      "al-q-003187",
      "al-q-000453",
      "al-q-000373"
    ],
    "tags": [
      "知识解释"
    ],
    "updatedAt": "2026-07-03T00:00:00.000Z",
    "timeLimitMinutes": 60,
    "summary": "知识解释进阶",
    "description": "知识解释进阶",
    "slug": "知识解释进阶"
  },
  {
    "id": "al-exam-88",
    "title": "题目自测进阶",
    "difficulty": "hard",
    "timeLimit": 60,
    "totalScore": 100,
    "passingScore": 60,
    "questionIds": [
      "al-q-000519",
      "al-q-002112",
      "al-q-000100",
      "al-q-000849",
      "al-q-000924",
      "al-q-000919",
      "al-q-002725",
      "al-q-002488",
      "al-q-002611",
      "al-q-001367",
      "al-q-002859",
      "al-q-003092",
      "al-q-003226",
      "al-q-000440",
      "al-q-003321",
      "al-q-000962",
      "al-q-001336",
      "al-q-002370",
      "al-q-000678",
      "al-q-000675",
      "al-q-001762",
      "al-q-002498",
      "al-q-001299",
      "al-q-001224",
      "al-q-002333"
    ],
    "tags": [
      "题目自测"
    ],
    "updatedAt": "2026-07-03T00:00:00.000Z",
    "timeLimitMinutes": 60,
    "summary": "题目自测进阶",
    "description": "题目自测进阶",
    "slug": "题目自测进阶"
  },
  {
    "id": "al-exam-89",
    "title": "笔记总结进阶",
    "difficulty": "hard",
    "timeLimit": 60,
    "totalScore": 100,
    "passingScore": 60,
    "questionIds": [
      "al-q-003068",
      "al-q-000153",
      "al-q-001098",
      "al-q-000005",
      "al-q-000820",
      "al-q-003405",
      "al-q-002074",
      "al-q-002138",
      "al-q-000497",
      "al-q-001687",
      "al-q-002520",
      "al-q-000730",
      "al-q-003231",
      "al-q-001483",
      "al-q-001835",
      "al-q-002672",
      "al-q-003127",
      "al-q-001988",
      "al-q-002021",
      "al-q-003075",
      "al-q-002561",
      "al-q-003498",
      "al-q-002355",
      "al-q-002958",
      "al-q-000961"
    ],
    "tags": [
      "笔记总结"
    ],
    "updatedAt": "2026-07-03T00:00:00.000Z",
    "timeLimitMinutes": 60,
    "summary": "笔记总结进阶",
    "description": "笔记总结进阶",
    "slug": "笔记总结进阶"
  },
  {
    "id": "al-exam-90",
    "title": "编程辅助进阶",
    "difficulty": "hard",
    "timeLimit": 60,
    "totalScore": 100,
    "passingScore": 60,
    "questionIds": [
      "al-q-000692",
      "al-q-003028",
      "al-q-002832",
      "al-q-000378",
      "al-q-000428",
      "al-q-000645",
      "al-q-001779",
      "al-q-003002",
      "al-q-003191",
      "al-q-002334",
      "al-q-001160",
      "al-q-003326",
      "al-q-001892",
      "al-q-003019",
      "al-q-002841",
      "al-q-003029",
      "al-q-000744",
      "al-q-002598",
      "al-q-000464",
      "al-q-000643",
      "al-q-002713",
      "al-q-002427",
      "al-q-001944",
      "al-q-000510",
      "al-q-000223"
    ],
    "tags": [
      "编程辅助"
    ],
    "updatedAt": "2026-07-03T00:00:00.000Z",
    "timeLimitMinutes": 60,
    "summary": "编程辅助进阶",
    "description": "编程辅助进阶",
    "slug": "编程辅助进阶"
  },
  {
    "id": "al-exam-91",
    "title": "学科场景进阶",
    "difficulty": "hard",
    "timeLimit": 60,
    "totalScore": 100,
    "passingScore": 60,
    "questionIds": [
      "al-q-002916",
      "al-q-000480",
      "al-q-001002",
      "al-q-001794",
      "al-q-000836",
      "al-q-002707",
      "al-q-002550",
      "al-q-003015",
      "al-q-003381",
      "al-q-000628",
      "al-q-000652",
      "al-q-001866",
      "al-q-002292",
      "al-q-001279",
      "al-q-001600",
      "al-q-000966",
      "al-q-001720",
      "al-q-000380",
      "al-q-000707",
      "al-q-001826",
      "al-q-001700",
      "al-q-003283",
      "al-q-003298",
      "al-q-002066",
      "al-q-001419"
    ],
    "tags": [
      "学科场景"
    ],
    "updatedAt": "2026-07-03T00:00:00.000Z",
    "timeLimitMinutes": 60,
    "summary": "学科场景进阶",
    "description": "学科场景进阶",
    "slug": "学科场景进阶"
  },
  {
    "id": "al-exam-92",
    "title": "项目辅助进阶",
    "difficulty": "hard",
    "timeLimit": 60,
    "totalScore": 100,
    "passingScore": 60,
    "questionIds": [
      "al-q-001610",
      "al-q-002955",
      "al-q-002764",
      "al-q-001561",
      "al-q-002312",
      "al-q-001365",
      "al-q-002919",
      "al-q-002681",
      "al-q-000873",
      "al-q-000321",
      "al-q-002164",
      "al-q-000282",
      "al-q-000914",
      "al-q-000948",
      "al-q-000425",
      "al-q-003487",
      "al-q-002609",
      "al-q-003361",
      "al-q-001534",
      "al-q-001884",
      "al-q-001304",
      "al-q-002016",
      "al-q-001842",
      "al-q-003014",
      "al-q-003413"
    ],
    "tags": [
      "项目辅助"
    ],
    "updatedAt": "2026-07-03T00:00:00.000Z",
    "timeLimitMinutes": 60,
    "summary": "项目辅助进阶",
    "description": "项目辅助进阶",
    "slug": "项目辅助进阶"
  },
  {
    "id": "al-exam-93",
    "title": "事实核查进阶",
    "difficulty": "hard",
    "timeLimit": 60,
    "totalScore": 100,
    "passingScore": 60,
    "questionIds": [
      "al-q-000146",
      "al-q-001795",
      "al-q-001668",
      "al-q-002570",
      "al-q-002013",
      "al-q-002575",
      "al-q-003027",
      "al-q-002162",
      "al-q-002530",
      "al-q-002777",
      "al-q-002847",
      "al-q-000954",
      "al-q-003216",
      "al-q-002175",
      "al-q-001215",
      "al-q-001981",
      "al-q-003000",
      "al-q-003472",
      "al-q-001164",
      "al-q-002443",
      "al-q-000079",
      "al-q-000989",
      "al-q-000938",
      "al-q-000546",
      "al-q-001432"
    ],
    "tags": [
      "事实核查"
    ],
    "updatedAt": "2026-07-03T00:00:00.000Z",
    "timeLimitMinutes": 60,
    "summary": "事实核查进阶",
    "description": "事实核查进阶",
    "slug": "事实核查进阶"
  },
  {
    "id": "al-exam-94",
    "title": "工作流模板进阶",
    "difficulty": "hard",
    "timeLimit": 60,
    "totalScore": 100,
    "passingScore": 60,
    "questionIds": [
      "al-q-002578",
      "al-q-001670",
      "al-q-000104",
      "al-q-001806",
      "al-q-000660",
      "al-q-003116",
      "al-q-001851",
      "al-q-001448",
      "al-q-001538",
      "al-q-000971",
      "al-q-001370",
      "al-q-001086",
      "al-q-001877",
      "al-q-003273",
      "al-q-002365",
      "al-q-000391",
      "al-q-003250",
      "al-q-002486",
      "al-q-002084",
      "al-q-001251",
      "al-q-003172",
      "al-q-003105",
      "al-q-003147",
      "al-q-001177",
      "al-q-002654"
    ],
    "tags": [
      "工作流模板"
    ],
    "updatedAt": "2026-07-03T00:00:00.000Z",
    "timeLimitMinutes": 60,
    "summary": "工作流模板进阶",
    "description": "工作流模板进阶",
    "slug": "工作流模板进阶"
  },
  {
    "id": "al-exam-95",
    "title": "学习日志进阶",
    "difficulty": "hard",
    "timeLimit": 60,
    "totalScore": 100,
    "passingScore": 60,
    "questionIds": [
      "al-q-000307",
      "al-q-001288",
      "al-q-002524",
      "al-q-003389",
      "al-q-003428",
      "al-q-003371",
      "al-q-001139",
      "al-q-000200",
      "al-q-002539",
      "al-q-002646",
      "al-q-002815",
      "al-q-003196",
      "al-q-000934",
      "al-q-002147",
      "al-q-002169",
      "al-q-002780",
      "al-q-000431",
      "al-q-000221",
      "al-q-002969",
      "al-q-002767",
      "al-q-001120",
      "al-q-001415",
      "al-q-000242",
      "al-q-000632",
      "al-q-002940"
    ],
    "tags": [
      "学习日志"
    ],
    "updatedAt": "2026-07-03T00:00:00.000Z",
    "timeLimitMinutes": 60,
    "summary": "学习日志进阶",
    "description": "学习日志进阶",
    "slug": "学习日志进阶"
  },
  {
    "id": "al-exam-96",
    "title": "输出评估进阶",
    "difficulty": "hard",
    "timeLimit": 60,
    "totalScore": 100,
    "passingScore": 60,
    "questionIds": [
      "al-q-002553",
      "al-q-002878",
      "al-q-003380",
      "al-q-001909",
      "al-q-000781",
      "al-q-001830",
      "al-q-002238",
      "al-q-001855",
      "al-q-003464",
      "al-q-002807",
      "al-q-000883",
      "al-q-003423",
      "al-q-000481",
      "al-q-002913",
      "al-q-002036",
      "al-q-000054",
      "al-q-002192",
      "al-q-000950",
      "al-q-002992",
      "al-q-001433",
      "al-q-000304",
      "al-q-001539",
      "al-q-001854",
      "al-q-000387",
      "al-q-002180"
    ],
    "tags": [
      "输出评估"
    ],
    "updatedAt": "2026-07-03T00:00:00.000Z",
    "timeLimitMinutes": 60,
    "summary": "输出评估进阶",
    "description": "输出评估进阶",
    "slug": "输出评估进阶"
  },
  {
    "id": "al-exam-97",
    "title": "安全规范进阶",
    "difficulty": "hard",
    "timeLimit": 60,
    "totalScore": 100,
    "passingScore": 60,
    "questionIds": [
      "al-q-003122",
      "al-q-003398",
      "al-q-002477",
      "al-q-003244",
      "al-q-002710",
      "al-q-002650",
      "al-q-001412",
      "al-q-000864",
      "al-q-001032",
      "al-q-001043",
      "al-q-000704",
      "al-q-001153",
      "al-q-002288",
      "al-q-002543",
      "al-q-003363",
      "al-q-002513",
      "al-q-000178",
      "al-q-002730",
      "al-q-002454",
      "al-q-000246",
      "al-q-003412",
      "al-q-003276",
      "al-q-002935",
      "al-q-001883",
      "al-q-003439"
    ],
    "tags": [
      "安全规范"
    ],
    "updatedAt": "2026-07-03T00:00:00.000Z",
    "timeLimitMinutes": 60,
    "summary": "安全规范进阶",
    "description": "安全规范进阶",
    "slug": "安全规范进阶"
  },
  {
    "id": "al-exam-98",
    "title": "AI综合进阶",
    "difficulty": "hard",
    "timeLimit": 60,
    "totalScore": 100,
    "passingScore": 60,
    "questionIds": [
      "al-q-001312",
      "al-q-002248",
      "al-q-001284",
      "al-q-001060",
      "al-q-002623",
      "al-q-001566",
      "al-q-002852",
      "al-q-001873",
      "al-q-002491",
      "al-q-000338",
      "al-q-002572",
      "al-q-001390",
      "al-q-000558",
      "al-q-001468",
      "al-q-002191",
      "al-q-000912",
      "al-q-002835",
      "al-q-002961",
      "al-q-002111",
      "al-q-000583",
      "al-q-003125",
      "al-q-002065",
      "al-q-002563",
      "al-q-001282",
      "al-q-001918"
    ],
    "tags": [
      "AI综合"
    ],
    "updatedAt": "2026-07-03T00:00:00.000Z",
    "timeLimitMinutes": 60,
    "summary": "AI综合进阶",
    "description": "AI综合进阶",
    "slug": "ai综合进阶"
  },
  {
    "id": "al-exam-99",
    "title": "AI入门进阶",
    "difficulty": "hard",
    "timeLimit": 60,
    "totalScore": 100,
    "passingScore": 60,
    "questionIds": [
      "al-q-002213",
      "al-q-001837",
      "al-q-000620",
      "al-q-002268",
      "al-q-001651",
      "al-q-002722",
      "al-q-003460",
      "al-q-001882",
      "al-q-002745",
      "al-q-000544",
      "al-q-003338",
      "al-q-002883",
      "al-q-000616",
      "al-q-002521",
      "al-q-001302",
      "al-q-002107",
      "al-q-002273",
      "al-q-000951",
      "al-q-002527",
      "al-q-001775",
      "al-q-000347",
      "al-q-002437",
      "al-q-002882",
      "al-q-000191",
      "al-q-003076"
    ],
    "tags": [
      "AI入门"
    ],
    "updatedAt": "2026-07-03T00:00:00.000Z",
    "timeLimitMinutes": 60,
    "summary": "AI入门进阶",
    "description": "AI入门进阶",
    "slug": "ai入门进阶"
  },
  {
    "id": "al-exam-100",
    "title": "学习计划进阶",
    "difficulty": "hard",
    "timeLimit": 60,
    "totalScore": 100,
    "passingScore": 60,
    "questionIds": [
      "al-q-001005",
      "al-q-003387",
      "al-q-001622",
      "al-q-000556",
      "al-q-002018",
      "al-q-000118",
      "al-q-001969",
      "al-q-003058",
      "al-q-000101",
      "al-q-001296",
      "al-q-002640",
      "al-q-000773",
      "al-q-001846",
      "al-q-001594",
      "al-q-003248",
      "al-q-002089",
      "al-q-002082",
      "al-q-002584",
      "al-q-001946",
      "al-q-001418",
      "al-q-003323",
      "al-q-002793",
      "al-q-001341",
      "al-q-000084",
      "al-q-000208"
    ],
    "tags": [
      "学习计划"
    ],
    "updatedAt": "2026-07-03T00:00:00.000Z",
    "timeLimitMinutes": 60,
    "summary": "学习计划进阶",
    "description": "学习计划进阶",
    "slug": "学习计划进阶"
  }
]